{
"meta":{"test_sets":[],"test_metrics":[],"learn_metrics":[{"best_value":"Min","name":"RMSE"}],"launch_mode":"Train","parameters":"","iteration_count":1000,"learn_sets":["learn"],"name":"experiment"},
"iterations":[
{"learn":[0.3015545006],"iteration":0,"passed_time":0.04711010518,"remaining_time":47.06299507},
{"learn":[0.3007120365],"iteration":1,"passed_time":0.0475995623,"remaining_time":23.75218159},
{"learn":[0.299827907],"iteration":2,"passed_time":0.04784901492,"remaining_time":15.90182262},
{"learn":[0.2988928398],"iteration":3,"passed_time":0.04829923812,"remaining_time":12.02651029},
{"learn":[0.297977253],"iteration":4,"passed_time":0.04867038129,"remaining_time":9.685405877},
{"learn":[0.2970565093],"iteration":5,"passed_time":0.04908402499,"remaining_time":8.131586806},
{"learn":[0.2962072228],"iteration":6,"passed_time":0.04948941304,"remaining_time":7.020426736},
{"learn":[0.2952558131],"iteration":7,"passed_time":0.0498724788,"remaining_time":6.184187372},
{"learn":[0.2945805155],"iteration":8,"passed_time":0.05029407757,"remaining_time":5.537936763},
{"learn":[0.293937412],"iteration":9,"passed_time":0.05066995992,"remaining_time":5.016326032},
{"learn":[0.2931423052],"iteration":10,"passed_time":0.05109560636,"remaining_time":4.593959517},
{"learn":[0.2925449278],"iteration":11,"passed_time":0.05147011591,"remaining_time":4.23770621},
{"learn":[0.2917538831],"iteration":12,"passed_time":0.05188484165,"remaining_time":3.939256824},
{"learn":[0.2910233877],"iteration":13,"passed_time":0.05230610959,"remaining_time":3.683844575},
{"learn":[0.2904280848],"iteration":14,"passed_time":0.05270842161,"remaining_time":3.461186352},
{"learn":[0.2897960735],"iteration":15,"passed_time":0.05313957849,"remaining_time":3.268084077},
{"learn":[0.2892893484],"iteration":16,"passed_time":0.05354365426,"remaining_time":3.096083067},
{"learn":[0.2888245572],"iteration":17,"passed_time":0.05394342146,"remaining_time":2.942913326},
{"learn":[0.288373969],"iteration":18,"passed_time":0.05432856094,"remaining_time":2.805069383},
{"learn":[0.2877218923],"iteration":19,"passed_time":0.05474205415,"remaining_time":2.682360653},
{"learn":[0.2872453414],"iteration":20,"passed_time":0.05514672083,"remaining_time":2.570887605},
{"learn":[0.2867351572],"iteration":21,"passed_time":0.0555544934,"remaining_time":2.469649752},
{"learn":[0.2862116351],"iteration":22,"passed_time":0.05594260873,"remaining_time":2.376344727},
{"learn":[0.2857769021],"iteration":23,"passed_time":0.05630696926,"remaining_time":2.28981675},
{"learn":[0.2853297325],"iteration":24,"passed_time":0.05670991268,"remaining_time":2.211686595},
{"learn":[0.284970024],"iteration":25,"passed_time":0.05709511228,"remaining_time":2.138870745},
{"learn":[0.2846913382],"iteration":26,"passed_time":0.05750482853,"remaining_time":2.072303636},
{"learn":[0.2842314439],"iteration":27,"passed_time":0.05789168147,"remaining_time":2.009668371},
{"learn":[0.2839054604],"iteration":28,"passed_time":0.05826711277,"remaining_time":1.950943672},
{"learn":[0.283352174],"iteration":29,"passed_time":0.05867856251,"remaining_time":1.897273521},
{"learn":[0.2829519039],"iteration":30,"passed_time":0.05906020557,"remaining_time":1.846107716},
{"learn":[0.2827169884],"iteration":31,"passed_time":0.05945275952,"remaining_time":1.798445975},
{"learn":[0.2823605817],"iteration":32,"passed_time":0.05984190659,"remaining_time":1.753549202},
{"learn":[0.2819480916],"iteration":33,"passed_time":0.06025183345,"remaining_time":1.711860915},
{"learn":[0.2818010706],"iteration":34,"passed_time":0.0606305612,"remaining_time":1.671671187},
{"learn":[0.2810691392],"iteration":35,"passed_time":0.06103084979,"remaining_time":1.634270533},
{"learn":[0.2809140069],"iteration":36,"passed_time":0.06143053725,"remaining_time":1.598854253},
{"learn":[0.2806688576],"iteration":37,"passed_time":0.06181940421,"remaining_time":1.565007022},
{"learn":[0.2804273857],"iteration":38,"passed_time":0.0622145226,"remaining_time":1.533029647},
{"learn":[0.2801720184],"iteration":39,"passed_time":0.06259279929,"remaining_time":1.502227183},
{"learn":[0.2799348403],"iteration":40,"passed_time":0.06296927256,"remaining_time":1.472866643},
{"learn":[0.279639527],"iteration":41,"passed_time":0.06339257455,"remaining_time":1.445954439},
{"learn":[0.2794606934],"iteration":42,"passed_time":0.06377872616,"remaining_time":1.419447464},
{"learn":[0.2792043931],"iteration":43,"passed_time":0.06419185909,"remaining_time":1.394714029},
{"learn":[0.2789099494],"iteration":44,"passed_time":0.06458167764,"remaining_time":1.370566714},
{"learn":[0.2786470187],"iteration":45,"passed_time":0.06500212443,"remaining_time":1.348087537},
{"learn":[0.2784493589],"iteration":46,"passed_time":0.0653959608,"remaining_time":1.326007461},
{"learn":[0.2783268268],"iteration":47,"passed_time":0.06579020775,"remaining_time":1.30483912},
{"learn":[0.2781200064],"iteration":48,"passed_time":0.06619962343,"remaining_time":1.2848131},
{"learn":[0.2777473909],"iteration":49,"passed_time":0.06658955199,"remaining_time":1.265201488},
{"learn":[0.2775755004],"iteration":50,"passed_time":0.0669904315,"remaining_time":1.246547441},
{"learn":[0.2774151333],"iteration":51,"passed_time":0.06736645412,"remaining_time":1.228142279},
{"learn":[0.2771448032],"iteration":52,"passed_time":0.06776845576,"remaining_time":1.210881653},
{"learn":[0.2769382381],"iteration":53,"passed_time":0.06816935531,"remaining_time":1.194226113},
{"learn":[0.2768608684],"iteration":54,"passed_time":0.06856098709,"remaining_time":1.178002415},
{"learn":[0.2765293322],"iteration":55,"passed_time":0.06898439909,"remaining_time":1.16287987},
{"learn":[0.2764440904],"iteration":56,"passed_time":0.06925186584,"remaining_time":1.145693149},
{"learn":[0.2762778551],"iteration":57,"passed_time":0.06970569587,"remaining_time":1.132116647},
{"learn":[0.2761419559],"iteration":58,"passed_time":0.07009992278,"remaining_time":1.118034362},
{"learn":[0.2758208632],"iteration":59,"passed_time":0.07049825747,"remaining_time":1.1044727},
{"learn":[0.2756661627],"iteration":60,"passed_time":0.07087899883,"remaining_time":1.091071802},
{"learn":[0.2754654039],"iteration":61,"passed_time":0.07126983932,"remaining_time":1.078243698},
{"learn":[0.2753208507],"iteration":62,"passed_time":0.07165987829,"remaining_time":1.065798507},
{"learn":[0.275206258],"iteration":63,"passed_time":0.07204663104,"remaining_time":1.053681979},
{"learn":[0.2750162115],"iteration":64,"passed_time":0.0724572993,"remaining_time":1.042270382},
{"learn":[0.2747829348],"iteration":65,"passed_time":0.07284957271,"remaining_time":1.030931832},
{"learn":[0.2745680567],"iteration":66,"passed_time":0.07324603405,"remaining_time":1.019978355},
{"learn":[0.2743707613],"iteration":67,"passed_time":0.07365489849,"remaining_time":1.009505373},
{"learn":[0.2741819704],"iteration":68,"passed_time":0.07405493641,"remaining_time":0.9992050115},
{"learn":[0.2739926515],"iteration":69,"passed_time":0.07445691801,"remaining_time":0.9892133392},
{"learn":[0.2737972499],"iteration":70,"passed_time":0.07484917097,"remaining_time":0.9793645046},
{"learn":[0.2736772314],"iteration":71,"passed_time":0.07524955975,"remaining_time":0.9698832146},
{"learn":[0.273403201],"iteration":72,"passed_time":0.07565406614,"remaining_time":0.9607030042},
{"learn":[0.2732866906],"iteration":73,"passed_time":0.07603928577,"remaining_time":0.9515186301},
{"learn":[0.2729850293],"iteration":74,"passed_time":0.07644861108,"remaining_time":0.9428662034},
{"learn":[0.2727886262],"iteration":75,"passed_time":0.07682939252,"remaining_time":0.9340836669},
{"learn":[0.272655851],"iteration":76,"passed_time":0.07721903073,"remaining_time":0.9256255242},
{"learn":[0.2723308647],"iteration":77,"passed_time":0.07760937027,"remaining_time":0.9173825563},
{"learn":[0.2721742985],"iteration":78,"passed_time":0.07801425738,"remaining_time":0.9095079879},
{"learn":[0.2718850846],"iteration":79,"passed_time":0.07839708268,"remaining_time":0.9015664508},
{"learn":[0.2716703253],"iteration":80,"passed_time":0.07879564801,"remaining_time":0.8939901299},
{"learn":[0.2714995924],"iteration":81,"passed_time":0.07921109512,"remaining_time":0.8867778698},
{"learn":[0.2714692509],"iteration":82,"passed_time":0.07942897772,"remaining_time":0.8775466575},
{"learn":[0.2712629444],"iteration":83,"passed_time":0.07981987833,"remaining_time":0.8704167684},
{"learn":[0.271038685],"iteration":84,"passed_time":0.08020634073,"remaining_time":0.8633976678},
{"learn":[0.2708810297],"iteration":85,"passed_time":0.08059732148,"remaining_time":0.8565808353},
{"learn":[0.2707161691],"iteration":86,"passed_time":0.08100320026,"remaining_time":0.8500680671},
{"learn":[0.2705170478],"iteration":87,"passed_time":0.08140744615,"remaining_time":0.8436771692},
{"learn":[0.2704516119],"iteration":88,"passed_time":0.08180624172,"remaining_time":0.8373650135},
{"learn":[0.2703817115],"iteration":89,"passed_time":0.08219641114,"remaining_time":0.831097046},
{"learn":[0.2702396459],"iteration":90,"passed_time":0.0825952067,"remaining_time":0.8250444274},
{"learn":[0.2699136712],"iteration":91,"passed_time":0.08300693657,"remaining_time":0.8192423739},
{"learn":[0.2698329894],"iteration":92,"passed_time":0.08340010146,"remaining_time":0.8133751831},
{"learn":[0.2695277406],"iteration":93,"passed_time":0.0838119217,"remaining_time":0.8078042666},
{"learn":[0.2694185643],"iteration":94,"passed_time":0.08418566981,"remaining_time":0.8019792755},
{"learn":[0.2692818478],"iteration":95,"passed_time":0.08459923335,"remaining_time":0.7966427807},
{"learn":[0.2691295443],"iteration":96,"passed_time":0.0849689939,"remaining_time":0.7910000154},
{"learn":[0.2687673234],"iteration":97,"passed_time":0.08536080644,"remaining_time":0.7856678307},
{"learn":[0.2685124208],"iteration":98,"passed_time":0.08579400719,"remaining_time":0.780812126},
{"learn":[0.2682628656],"iteration":99,"passed_time":0.0862015393,"remaining_time":0.7758138537},
{"learn":[0.2679800639],"iteration":100,"passed_time":0.08660287969,"remaining_time":0.7708513747},
{"learn":[0.2677609044],"iteration":101,"passed_time":0.08700401969,"remaining_time":0.7659765655},
{"learn":[0.267491739],"iteration":102,"passed_time":0.0874047389,"remaining_time":0.7611849592},
{"learn":[0.2672449084],"iteration":103,"passed_time":0.08779695179,"remaining_time":0.7564045077},
{"learn":[0.2670220166],"iteration":104,"passed_time":0.08820998453,"remaining_time":0.7518851062},
{"learn":[0.2667659573],"iteration":105,"passed_time":0.08859862084,"remaining_time":0.7472374249},
{"learn":[0.266686358],"iteration":106,"passed_time":0.08898201703,"remaining_time":0.7426256187},
{"learn":[0.266569045],"iteration":107,"passed_time":0.08939094199,"remaining_time":0.7383029653},
{"learn":[0.2663310858],"iteration":108,"passed_time":0.08978692201,"remaining_time":0.7339463074},
{"learn":[0.2662748225],"iteration":109,"passed_time":0.09021405125,"remaining_time":0.7299136874},
{"learn":[0.2661085241],"iteration":110,"passed_time":0.09060790766,"remaining_time":0.7256795488},
{"learn":[0.2659816627],"iteration":111,"passed_time":0.09101343598,"remaining_time":0.7216065281},
{"learn":[0.2658387658],"iteration":112,"passed_time":0.09141622891,"remaining_time":0.7175769473},
{"learn":[0.2654429426],"iteration":113,"passed_time":0.09180089771,"remaining_time":0.7134701349},
{"learn":[0.2650734488],"iteration":114,"passed_time":0.09222444998,"remaining_time":0.7097272889},
{"learn":[0.2648869451],"iteration":115,"passed_time":0.0926407988,"remaining_time":0.705986777},
{"learn":[0.2646951184],"iteration":116,"passed_time":0.09306881952,"remaining_time":0.7023911764},
{"learn":[0.264552039],"iteration":117,"passed_time":0.09346700373,"remaining_time":0.6986262482},
{"learn":[0.2644753739],"iteration":118,"passed_time":0.09388416429,"remaining_time":0.6950583927},
{"learn":[0.2642164239],"iteration":119,"passed_time":0.09428477308,"remaining_time":0.6914216693},
{"learn":[0.2641136193],"iteration":120,"passed_time":0.09468288735,"remaining_time":0.6878203139},
{"learn":[0.2640099288],"iteration":121,"passed_time":0.09513476348,"remaining_time":0.6846583798},
{"learn":[0.2638061242],"iteration":122,"passed_time":0.09552674614,"remaining_time":0.6811134664},
{"learn":[0.2635384563],"iteration":123,"passed_time":0.09594294488,"remaining_time":0.6777904816},
{"learn":[0.2634964033],"iteration":124,"passed_time":0.09615875375,"remaining_time":0.6731112763},
{"learn":[0.2632139184],"iteration":125,"passed_time":0.09654945398,"remaining_time":0.6697160538},
{"learn":[0.2629175633],"iteration":126,"passed_time":0.09698130237,"remaining_time":0.6666509997},
{"learn":[0.2627450431],"iteration":127,"passed_time":0.09736452843,"remaining_time":0.6632958499},
{"learn":[0.2625473223],"iteration":128,"passed_time":0.0977733029,"remaining_time":0.6601592777},
{"learn":[0.2622801779],"iteration":129,"passed_time":0.09816381297,"remaining_time":0.6569424406},
{"learn":[0.2621607211],"iteration":130,"passed_time":0.09856788874,"remaining_time":0.6538587429},
{"learn":[0.2618147795],"iteration":131,"passed_time":0.09897077205,"remaining_time":0.6508078041},
{"learn":[0.2615011436],"iteration":132,"passed_time":0.09936897629,"remaining_time":0.6477661838},
{"learn":[0.2613145396],"iteration":133,"passed_time":0.09979273915,"remaining_time":0.6449291948},
{"learn":[0.2609303581],"iteration":134,"passed_time":0.1002085568,"remaining_time":0.6420770489},
{"learn":[0.2608534319],"iteration":135,"passed_time":0.1006114801,"remaining_time":0.639178815},
{"learn":[0.2607674548],"iteration":136,"passed_time":0.1009904381,"remaining_time":0.6361660445},
{"learn":[0.2605111609],"iteration":137,"passed_time":0.1013973491,"remaining_time":0.6333660499},
{"learn":[0.2604383366],"iteration":138,"passed_time":0.1017818976,"remaining_time":0.6304619702},
{"learn":[0.2603200699],"iteration":139,"passed_time":0.1021567478,"remaining_time":0.6275343081},
{"learn":[0.2602457869],"iteration":140,"passed_time":0.1026217288,"remaining_time":0.6251919506},
{"learn":[0.2601202571],"iteration":141,"passed_time":0.1031425355,"remaining_time":0.6232133484},
{"learn":[0.2600262309],"iteration":142,"passed_time":0.1036337462,"remaining_time":0.6210777655},
{"learn":[0.2598414107],"iteration":143,"passed_time":0.104157889,"remaining_time":0.6191607847},
{"learn":[0.259718091],"iteration":144,"passed_time":0.1045508437,"remaining_time":0.6164894577},
{"learn":[0.2595970009],"iteration":145,"passed_time":0.1049475353,"remaining_time":0.6138711996},
{"learn":[0.2595703695],"iteration":146,"passed_time":0.105226995,"remaining_time":0.6106029027},
{"learn":[0.259453271],"iteration":147,"passed_time":0.1055980882,"remaining_time":0.607902508},
{"learn":[0.2593463811],"iteration":148,"passed_time":0.106001212,"remaining_time":0.6054163182},
{"learn":[0.2589656328],"iteration":149,"passed_time":0.1064020416,"remaining_time":0.6029449025},
{"learn":[0.2587165848],"iteration":150,"passed_time":0.1068108259,"remaining_time":0.6005456371},
{"learn":[0.2586479396],"iteration":151,"passed_time":0.1072194601,"remaining_time":0.5981717248},
{"learn":[0.2584610171],"iteration":152,"passed_time":0.1076181956,"remaining_time":0.5957687035},
{"learn":[0.2582160996],"iteration":153,"passed_time":0.1080333519,"remaining_time":0.5934819203},
{"learn":[0.2579734494],"iteration":154,"passed_time":0.1084369864,"remaining_time":0.5911564745},
{"learn":[0.2578661177],"iteration":155,"passed_time":0.1088416732,"remaining_time":0.58886136},
{"learn":[0.2577903218],"iteration":156,"passed_time":0.1092383746,"remaining_time":0.5865474507},
{"learn":[0.2576944782],"iteration":157,"passed_time":0.1096224422,"remaining_time":0.5841904832},
{"learn":[0.2573901226],"iteration":158,"passed_time":0.1100410553,"remaining_time":0.5820410537},
{"learn":[0.2571957145],"iteration":159,"passed_time":0.1104341503,"remaining_time":0.5797792891},
{"learn":[0.2569739971],"iteration":160,"passed_time":0.1108489664,"remaining_time":0.5776539306},
{"learn":[0.2566287612],"iteration":161,"passed_time":0.1112475714,"remaining_time":0.5754658324},
{"learn":[0.2565793556],"iteration":162,"passed_time":0.1116414777,"remaining_time":0.5732755635},
{"learn":[0.2561535766],"iteration":163,"passed_time":0.1120581169,"remaining_time":0.5712230836},
{"learn":[0.2559533829],"iteration":164,"passed_time":0.1124852862,"remaining_time":0.5692437211},
{"learn":[0.2556170473],"iteration":165,"passed_time":0.1128908546,"remaining_time":0.5671745345},
{"learn":[0.2554290598],"iteration":166,"passed_time":0.1132932468,"remaining_time":0.5651094285},
{"learn":[0.2552461576],"iteration":167,"passed_time":0.1137051369,"remaining_time":0.5631111543},
{"learn":[0.2551933336],"iteration":168,"passed_time":0.1140922704,"remaining_time":0.5610099213},
{"learn":[0.2551283944],"iteration":169,"passed_time":0.11450915,"remaining_time":0.5590740854},
{"learn":[0.2548646841],"iteration":170,"passed_time":0.1149144281,"remaining_time":0.5570997712},
{"learn":[0.2548296368],"iteration":171,"passed_time":0.1153074126,"remaining_time":0.5550845212},
{"learn":[0.2546327818],"iteration":172,"passed_time":0.1157232004,"remaining_time":0.553197033},
{"learn":[0.2545694339],"iteration":173,"passed_time":0.1161116261,"remaining_time":0.5511965699},
{"learn":[0.2544681268],"iteration":174,"passed_time":0.1165240377,"remaining_time":0.5493276061},
{"learn":[0.2542788808],"iteration":175,"passed_time":0.116929496,"remaining_time":0.5474426406},
{"learn":[0.2541783292],"iteration":176,"passed_time":0.117329554,"remaining_time":0.5455492822},
{"learn":[0.2541094378],"iteration":177,"passed_time":0.1177356336,"remaining_time":0.5437005101},
{"learn":[0.2539629695],"iteration":178,"passed_time":0.1181469827,"remaining_time":0.5418920269},
{"learn":[0.2539225458],"iteration":179,"passed_time":0.1185206805,"remaining_time":0.5399275446},
{"learn":[0.2538257189],"iteration":180,"passed_time":0.1189032952,"remaining_time":0.5380209878},
{"learn":[0.2536573095],"iteration":181,"passed_time":0.1193246936,"remaining_time":0.5363054911},
{"learn":[0.2534928239],"iteration":182,"passed_time":0.1197246015,"remaining_time":0.5345081935},
{"learn":[0.2532308695],"iteration":183,"passed_time":0.1201376543,"remaining_time":0.5327843798},
{"learn":[0.253034973],"iteration":184,"passed_time":0.1205361991,"remaining_time":0.5310108233},
{"learn":[0.2526100779],"iteration":185,"passed_time":0.1209507446,"remaining_time":0.5293220756},
{"learn":[0.2523798807],"iteration":186,"passed_time":0.1213616929,"remaining_time":0.5276313174},
{"learn":[0.2523279667],"iteration":187,"passed_time":0.1217467122,"remaining_time":0.5258421825},
{"learn":[0.2522380153],"iteration":188,"passed_time":0.1221581717,"remaining_time":0.5241813613},
{"learn":[0.2520933392],"iteration":189,"passed_time":0.1225682389,"remaining_time":0.5225277552},
{"learn":[0.2519406243],"iteration":190,"passed_time":0.1230011292,"remaining_time":0.5209838406},
{"learn":[0.2519261754],"iteration":191,"passed_time":0.1234067377,"remaining_time":0.5193366878},
{"learn":[0.2518233323],"iteration":192,"passed_time":0.1238135186,"remaining_time":0.5177073032},
{"learn":[0.2516871286],"iteration":193,"passed_time":0.1242135766,"remaining_time":0.5160625913},
{"learn":[0.2514296935],"iteration":194,"passed_time":0.1246040163,"remaining_time":0.514390939},
{"learn":[0.2513844657],"iteration":195,"passed_time":0.1249977623,"remaining_time":0.5127459228},
{"learn":[0.251139625],"iteration":196,"passed_time":0.1253858277,"remaining_time":0.5110904551},
{"learn":[0.2510430998],"iteration":197,"passed_time":0.1258052726,"remaining_time":0.5095748921},
{"learn":[0.2508980846],"iteration":198,"passed_time":0.126201363,"remaining_time":0.5079763407},
{"learn":[0.2507696727],"iteration":199,"passed_time":0.1266054286,"remaining_time":0.5064217144},
{"learn":[0.2505543629],"iteration":200,"passed_time":0.1270169781,"remaining_time":0.5049082862},
{"learn":[0.2505199458],"iteration":201,"passed_time":0.1273878808,"remaining_time":0.5032451926},
{"learn":[0.2503740257],"iteration":202,"passed_time":0.1278089586,"remaining_time":0.5017918227},
{"learn":[0.2503157943],"iteration":203,"passed_time":0.1281861332,"remaining_time":0.5001772649},
{"learn":[0.2500707874],"iteration":204,"passed_time":0.1285939659,"remaining_time":0.4986936726},
{"learn":[0.2498162878],"iteration":205,"passed_time":0.1289934428,"remaining_time":0.4971883182},
{"learn":[0.2494534038],"iteration":206,"passed_time":0.1294226559,"remaining_time":0.495807566},
{"learn":[0.2492981564],"iteration":207,"passed_time":0.1298162416,"remaining_time":0.4943003047},
{"learn":[0.2489685804],"iteration":208,"passed_time":0.1302081944,"remaining_time":0.4927975206},
{"learn":[0.2488878756],"iteration":209,"passed_time":0.1305968205,"remaining_time":0.4912928011},
{"learn":[0.2486587527],"iteration":210,"passed_time":0.1309911178,"remaining_time":0.489819867},
{"learn":[0.2484347723],"iteration":211,"passed_time":0.1314174054,"remaining_time":0.4884760164},
{"learn":[0.2484001106],"iteration":212,"passed_time":0.1317864148,"remaining_time":0.4869291475},
{"learn":[0.2481623485],"iteration":213,"passed_time":0.1321875347,"remaining_time":0.4855112257},
{"learn":[0.2480397173],"iteration":214,"passed_time":0.1325800985,"remaining_time":0.4840715224},
{"learn":[0.2477902277],"iteration":215,"passed_time":0.1329881418,"remaining_time":0.4826976998},
{"learn":[0.2477688753],"iteration":216,"passed_time":0.1333681417,"remaining_time":0.4812315897},
{"learn":[0.247729638],"iteration":217,"passed_time":0.1337323518,"remaining_time":0.4797188031},
{"learn":[0.2474234188],"iteration":218,"passed_time":0.134135065,"remaining_time":0.4783538161},
{"learn":[0.2472213074],"iteration":219,"passed_time":0.1345322976,"remaining_time":0.4769781459},
{"learn":[0.2470291542],"iteration":220,"passed_time":0.1349513715,"remaining_time":0.4756883187},
{"learn":[0.2470079719],"iteration":221,"passed_time":0.1353284259,"remaining_time":0.4742590782},
{"learn":[0.2468299815],"iteration":222,"passed_time":0.1357188256,"remaining_time":0.4728857734},
{"learn":[0.2466726077],"iteration":223,"passed_time":0.1361310167,"remaining_time":0.4715967365},
{"learn":[0.2464268886],"iteration":224,"passed_time":0.1365340902,"remaining_time":0.4702840884},
{"learn":[0.2464085724],"iteration":225,"passed_time":0.1369645257,"remaining_time":0.4690731986},
{"learn":[0.2461973073],"iteration":226,"passed_time":0.1373659761,"remaining_time":0.4677704824},
{"learn":[0.246111151],"iteration":227,"passed_time":0.1377682885,"remaining_time":0.4664785909},
{"learn":[0.2459221178],"iteration":228,"passed_time":0.1381655109,"remaining_time":0.4651773314},
{"learn":[0.2456894444],"iteration":229,"passed_time":0.1385646872,"remaining_time":0.4638904744},
{"learn":[0.2454616644],"iteration":230,"passed_time":0.138989492,"remaining_time":0.4626966206},
{"learn":[0.245443935],"iteration":231,"passed_time":0.1393744814,"remaining_time":0.4613775936},
{"learn":[0.2453326491],"iteration":232,"passed_time":0.1397810317,"remaining_time":0.4601375592},
{"learn":[0.2451939171],"iteration":233,"passed_time":0.1401956773,"remaining_time":0.4589311486},
{"learn":[0.2449636024],"iteration":234,"passed_time":0.1406190394,"remaining_time":0.4577598515},
{"learn":[0.2446642019],"iteration":235,"passed_time":0.1410232554,"remaining_time":0.4565329115},
{"learn":[0.2446508731],"iteration":236,"passed_time":0.1413816945,"remaining_time":0.4551655397},
{"learn":[0.2444858384],"iteration":237,"passed_time":0.1417961397,"remaining_time":0.4539859599},
{"learn":[0.2444284447],"iteration":238,"passed_time":0.1421796565,"remaining_time":0.4527143039},
{"learn":[0.2442946344],"iteration":239,"passed_time":0.1426231167,"remaining_time":0.4516398696},
{"learn":[0.2442459126],"iteration":240,"passed_time":0.1430123043,"remaining_time":0.4503997467},
{"learn":[0.2441745447],"iteration":241,"passed_time":0.1434093966,"remaining_time":0.4491914159},
{"learn":[0.2439705986],"iteration":242,"passed_time":0.1438109975,"remaining_time":0.448003807},
{"learn":[0.2437913918],"iteration":243,"passed_time":0.144217798,"remaining_time":0.4468387513},
{"learn":[0.2436719629],"iteration":244,"passed_time":0.144629608,"remaining_time":0.4456953227},
{"learn":[0.2436540409],"iteration":245,"passed_time":0.1450144572,"remaining_time":0.4444752062},
{"learn":[0.2434728254],"iteration":246,"passed_time":0.1454437804,"remaining_time":0.4433974357},
{"learn":[0.24336353],"iteration":247,"passed_time":0.1458327876,"remaining_time":0.4422026463},
{"learn":[0.2432306642],"iteration":248,"passed_time":0.146241502,"remaining_time":0.4410737669},
{"learn":[0.2429898711],"iteration":249,"passed_time":0.1466587427,"remaining_time":0.439976228},
{"learn":[0.2429325169],"iteration":250,"passed_time":0.1470551938,"remaining_time":0.4388220723},
{"learn":[0.2427570001],"iteration":251,"passed_time":0.1474545602,"remaining_time":0.4376825835},
{"learn":[0.2426972224],"iteration":252,"passed_time":0.1478438476,"remaining_time":0.4365191863},
{"learn":[0.2425912569],"iteration":253,"passed_time":0.148256269,"remaining_time":0.4354298293},
{"learn":[0.2422104277],"iteration":254,"passed_time":0.1486582403,"remaining_time":0.4343152512},
{"learn":[0.2420837739],"iteration":255,"passed_time":0.1490914713,"remaining_time":0.4332970886},
{"learn":[0.2418810864],"iteration":256,"passed_time":0.1495248524,"remaining_time":0.4322839119},
{"learn":[0.2416745298],"iteration":257,"passed_time":0.1499475635,"remaining_time":0.4312445431},
{"learn":[0.2416579908],"iteration":258,"passed_time":0.1503164322,"remaining_time":0.4300558928},
{"learn":[0.2414956965],"iteration":259,"passed_time":0.1506991573,"remaining_time":0.4289129861},
{"learn":[0.2413872472],"iteration":260,"passed_time":0.1511053068,"remaining_time":0.4278422288},
{"learn":[0.2412737311],"iteration":261,"passed_time":0.1515014876,"remaining_time":0.426748465},
{"learn":[0.2411545691],"iteration":262,"passed_time":0.1519163736,"remaining_time":0.4257124235},
{"learn":[0.240889472],"iteration":263,"passed_time":0.1523106508,"remaining_time":0.4246236326},
{"learn":[0.2406894177],"iteration":264,"passed_time":0.1527204971,"remaining_time":0.4235832656},
{"learn":[0.2404972919],"iteration":265,"passed_time":0.1531175294,"remaining_time":0.4225122803},
{"learn":[0.2403526735],"iteration":266,"passed_time":0.1535254925,"remaining_time":0.4214763521},
{"learn":[0.2403423662],"iteration":267,"passed_time":0.1539254805,"remaining_time":0.4204233274},
{"learn":[0.2402917405],"iteration":268,"passed_time":0.1543125637,"remaining_time":0.4193400894},
{"learn":[0.2401544813],"iteration":269,"passed_time":0.1547275602,"remaining_time":0.4183374774},
{"learn":[0.239954071],"iteration":270,"passed_time":0.1551222582,"remaining_time":0.4172845985},
{"learn":[0.2399088549],"iteration":271,"passed_time":0.1555096824,"remaining_time":0.4162170911},
{"learn":[0.2398042758],"iteration":272,"passed_time":0.1559016953,"remaining_time":0.4151667856},
{"learn":[0.2395788049],"iteration":273,"passed_time":0.1562954814,"remaining_time":0.4141259835},
{"learn":[0.2394258589],"iteration":274,"passed_time":0.1567170601,"remaining_time":0.4131631584},
{"learn":[0.2392691942],"iteration":275,"passed_time":0.1571160961,"remaining_time":0.4121451217},
{"learn":[0.239026705],"iteration":276,"passed_time":0.1575275459,"remaining_time":0.4111639554},
{"learn":[0.2388471206],"iteration":277,"passed_time":0.1579401774,"remaining_time":0.4101899572},
{"learn":[0.238643421],"iteration":278,"passed_time":0.1583704224,"remaining_time":0.4092655001},
{"learn":[0.2383381906],"iteration":279,"passed_time":0.1587655011,"remaining_time":0.4082541457},
{"learn":[0.238258995],"iteration":280,"passed_time":0.1591591367,"remaining_time":0.407243485},
{"learn":[0.2380287574],"iteration":281,"passed_time":0.1595826391,"remaining_time":0.4063132441},
{"learn":[0.2376873539],"iteration":282,"passed_time":0.1599898105,"remaining_time":0.4053452089},
{"learn":[0.237550866],"iteration":283,"passed_time":0.1604020315,"remaining_time":0.404393854},
{"learn":[0.2373313305],"iteration":284,"passed_time":0.160812409,"remaining_time":0.4034416576},
{"learn":[0.2371974415],"iteration":285,"passed_time":0.1612269646,"remaining_time":0.4025036809},
{"learn":[0.2370196786],"iteration":286,"passed_time":0.161638995,"remaining_time":0.4015630783},
{"learn":[0.2370030441],"iteration":287,"passed_time":0.1620322201,"remaining_time":0.4005796551},
{"learn":[0.2369880422],"iteration":288,"passed_time":0.1624117493,"remaining_time":0.399566622},
{"learn":[0.2368789575],"iteration":289,"passed_time":0.1628018787,"remaining_time":0.3985839098},
{"learn":[0.2367656705],"iteration":290,"passed_time":0.1632123163,"remaining_time":0.39765475},
{"learn":[0.2366560645],"iteration":291,"passed_time":0.1635961136,"remaining_time":0.3966645495},
{"learn":[0.2363345043],"iteration":292,"passed_time":0.164007884,"remaining_time":0.3957459863},
{"learn":[0.2360442144],"iteration":293,"passed_time":0.1644182517,"remaining_time":0.3948275023},
{"learn":[0.2360323207],"iteration":294,"passed_time":0.1647887937,"remaining_time":0.3938172867},
{"learn":[0.2359615604],"iteration":295,"passed_time":0.1651777805,"remaining_time":0.3928552617},
{"learn":[0.2359558964],"iteration":296,"passed_time":0.1655482722,"remaining_time":0.3918533178},
{"learn":[0.2357226704],"iteration":297,"passed_time":0.1659921229,"remaining_time":0.3910284239},
{"learn":[0.2355134316],"iteration":298,"passed_time":0.1663918104,"remaining_time":0.3901025388},
{"learn":[0.2354420737],"iteration":299,"passed_time":0.16679275,"remaining_time":0.3891830834},
{"learn":[0.2353158634],"iteration":300,"passed_time":0.1671838911,"remaining_time":0.3882443185},
{"learn":[0.2352041922],"iteration":301,"passed_time":0.1675689406,"remaining_time":0.3872951011},
{"learn":[0.2351950363],"iteration":302,"passed_time":0.1679551421,"remaining_time":0.3863522576},
{"learn":[0.2349511647],"iteration":303,"passed_time":0.1683587668,"remaining_time":0.3854529661},
{"learn":[0.2349202283],"iteration":304,"passed_time":0.1687674611,"remaining_time":0.384568477},
{"learn":[0.2347059854],"iteration":305,"passed_time":0.169170104,"remaining_time":0.3836733731},
{"learn":[0.2345703791],"iteration":306,"passed_time":0.1695902801,"remaining_time":0.3828210556},
{"learn":[0.2344678831],"iteration":307,"passed_time":0.1699893161,"remaining_time":0.3819240478},
{"learn":[0.2341749049],"iteration":308,"passed_time":0.1703872197,"remaining_time":0.3810277309},
{"learn":[0.2339669805],"iteration":309,"passed_time":0.1707772788,"remaining_time":0.3801171688},
{"learn":[0.2337789596],"iteration":310,"passed_time":0.1711776876,"remaining_time":0.3792328834},
{"learn":[0.2334763825],"iteration":311,"passed_time":0.1715973827,"remaining_time":0.3783942286},
{"learn":[0.2334356635],"iteration":312,"passed_time":0.1719793162,"remaining_time":0.377475368},
{"learn":[0.2333906628],"iteration":313,"passed_time":0.1724191593,"remaining_time":0.3766864435},
{"learn":[0.2332232155],"iteration":314,"passed_time":0.1728192974,"remaining_time":0.3758133927},
{"learn":[0.2329883247],"iteration":315,"passed_time":0.1732392829,"remaining_time":0.3749862959},
{"learn":[0.2328611128],"iteration":316,"passed_time":0.1736390501,"remaining_time":0.3741182057},
{"learn":[0.2328474366],"iteration":317,"passed_time":0.1740191801,"remaining_time":0.373210946},
{"learn":[0.2327244103],"iteration":318,"passed_time":0.1744372019,"remaining_time":0.3723878824},
{"learn":[0.232621377],"iteration":319,"passed_time":0.174846227,"remaining_time":0.3715482324},
{"learn":[0.2324920077],"iteration":320,"passed_time":0.1752520158,"remaining_time":0.3707044198},
{"learn":[0.2322164932],"iteration":321,"passed_time":0.1756635654,"remaining_time":0.3698754575},
{"learn":[0.2321345621],"iteration":322,"passed_time":0.1760661882,"remaining_time":0.3690303696},
{"learn":[0.2320999603],"iteration":323,"passed_time":0.1764396557,"remaining_time":0.368127183},
{"learn":[0.2320764383],"iteration":324,"passed_time":0.1768015115,"remaining_time":0.3672031393},
{"learn":[0.2318869723],"iteration":325,"passed_time":0.1772074304,"remaining_time":0.3663736444},
{"learn":[0.2317154483],"iteration":326,"passed_time":0.1776144215,"remaining_time":0.3655489469},
{"learn":[0.231619333],"iteration":327,"passed_time":0.1780374229,"remaining_time":0.3647595981},
{"learn":[0.2312426833],"iteration":328,"passed_time":0.1784317197,"remaining_time":0.3639139329},
{"learn":[0.2311579452],"iteration":329,"passed_time":0.1788420874,"remaining_time":0.363103632},
{"learn":[0.2310447127],"iteration":330,"passed_time":0.1792333585,"remaining_time":0.3622571506},
{"learn":[0.2310320804],"iteration":331,"passed_time":0.1796127471,"remaining_time":0.3613895032},
{"learn":[0.2308774661],"iteration":332,"passed_time":0.1800171333,"remaining_time":0.3605748585},
{"learn":[0.2305956344],"iteration":333,"passed_time":0.1804294843,"remaining_time":0.3597785525},
{"learn":[0.2304130961],"iteration":334,"passed_time":0.1808527262,"remaining_time":0.359006158},
{"learn":[0.2301968331],"iteration":335,"passed_time":0.1812491773,"remaining_time":0.358182898},
{"learn":[0.2300490436],"iteration":336,"passed_time":0.1816680812,"remaining_time":0.3574063437},
{"learn":[0.2297884329],"iteration":337,"passed_time":0.1820641618,"remaining_time":0.3565872045},
{"learn":[0.2295293185],"iteration":338,"passed_time":0.1824779458,"remaining_time":0.3558050801},
{"learn":[0.2292571355],"iteration":339,"passed_time":0.1829015381,"remaining_time":0.3550441622},
{"learn":[0.2291724334],"iteration":340,"passed_time":0.18329312,"remaining_time":0.3542233609},
{"learn":[0.2291074913],"iteration":341,"passed_time":0.1836870664,"remaining_time":0.3534096189},
{"learn":[0.2288986401],"iteration":342,"passed_time":0.1840903206,"remaining_time":0.3526161534},
{"learn":[0.2285283405],"iteration":343,"passed_time":0.184510587,"remaining_time":0.3518573985},
{"learn":[0.2283833843],"iteration":344,"passed_time":0.1849037617,"remaining_time":0.3510491708},
{"learn":[0.2282113582],"iteration":345,"passed_time":0.1853003629,"remaining_time":0.350249819},
{"learn":[0.2281591805],"iteration":346,"passed_time":0.1857194868,"remaining_time":0.3494951726},
{"learn":[0.2281192927],"iteration":347,"passed_time":0.1860964312,"remaining_time":0.3486634285},
{"learn":[0.2280268729],"iteration":348,"passed_time":0.1865088526,"remaining_time":0.3479004671},
{"learn":[0.22776847],"iteration":349,"passed_time":0.1869073275,"remaining_time":0.3471136082},
{"learn":[0.2276902653],"iteration":350,"passed_time":0.1873073654,"remaining_time":0.3463318523},
{"learn":[0.2276799123],"iteration":351,"passed_time":0.187668169,"remaining_time":0.3454800384},
{"learn":[0.2275068895],"iteration":352,"passed_time":0.1880705714,"remaining_time":0.3447072513},
{"learn":[0.2274959671],"iteration":353,"passed_time":0.1884600792,"remaining_time":0.3439130258},
{"learn":[0.2274379444],"iteration":354,"passed_time":0.1888277055,"remaining_time":0.343081324},
{"learn":[0.2272411414],"iteration":355,"passed_time":0.1892281744,"remaining_time":0.3423116414},
{"learn":[0.2272040924],"iteration":356,"passed_time":0.1896033951,"remaining_time":0.341498552},
{"learn":[0.2270259114],"iteration":357,"passed_time":0.1900025612,"remaining_time":0.3407308499},
{"learn":[0.2268488199],"iteration":358,"passed_time":0.1904115859,"remaining_time":0.3399828038},
{"learn":[0.2267445515],"iteration":359,"passed_time":0.1907998415,"remaining_time":0.3391997182},
{"learn":[0.2265744263],"iteration":360,"passed_time":0.191215599,"remaining_time":0.3384675007},
{"learn":[0.2263658393],"iteration":361,"passed_time":0.1916347732,"remaining_time":0.3377430533},
{"learn":[0.2259996249],"iteration":362,"passed_time":0.1920531258,"remaining_time":0.3370188461},
{"learn":[0.2256753296],"iteration":363,"passed_time":0.1924550976,"remaining_time":0.336267698},
{"learn":[0.2255961036],"iteration":364,"passed_time":0.1928616781,"remaining_time":0.3355264811},
{"learn":[0.2255119266],"iteration":365,"passed_time":0.1932608944,"remaining_time":0.3347743363},
{"learn":[0.225378676],"iteration":366,"passed_time":0.1936403235,"remaining_time":0.3339899858},
{"learn":[0.2251747172],"iteration":367,"passed_time":0.1940644172,"remaining_time":0.3332845426},
{"learn":[0.2250339484],"iteration":368,"passed_time":0.1944767282,"remaining_time":0.3325604756},
{"learn":[0.2248713521],"iteration":369,"passed_time":0.1948853321,"remaining_time":0.3318317817},
{"learn":[0.2247526535],"iteration":370,"passed_time":0.1952743794,"remaining_time":0.3310716568},
{"learn":[0.2246456303],"iteration":371,"passed_time":0.1956855785,"remaining_time":0.3303509228},
{"learn":[0.224640919],"iteration":372,"passed_time":0.1960586052,"remaining_time":0.3295676822},
{"learn":[0.2245359553],"iteration":373,"passed_time":0.1964536136,"remaining_time":0.3288234281},
{"learn":[0.2244806961],"iteration":374,"passed_time":0.1968595427,"remaining_time":0.3280992378},
{"learn":[0.2244469304],"iteration":375,"passed_time":0.1972393423,"remaining_time":0.3273333765},
{"learn":[0.2243570012],"iteration":376,"passed_time":0.1976427965,"remaining_time":0.326608653},
{"learn":[0.2241553755],"iteration":377,"passed_time":0.1980500681,"remaining_time":0.325891911},
{"learn":[0.223967886],"iteration":378,"passed_time":0.1984498152,"remaining_time":0.325164473},
{"learn":[0.2239525677],"iteration":379,"passed_time":0.1988302859,"remaining_time":0.3244073085},
{"learn":[0.2238393644],"iteration":380,"passed_time":0.1992412044,"remaining_time":0.3237015893},
{"learn":[0.2236931414],"iteration":381,"passed_time":0.1996531248,"remaining_time":0.3229990344},
{"learn":[0.2235414309],"iteration":382,"passed_time":0.2000553571,"remaining_time":0.3222823899},
{"learn":[0.2233301247],"iteration":383,"passed_time":0.200478078,"remaining_time":0.3216002501},
{"learn":[0.2232456715],"iteration":384,"passed_time":0.200871694,"remaining_time":0.3208729657},
{"learn":[0.2231179519],"iteration":385,"passed_time":0.201288664,"remaining_time":0.3201845587},
{"learn":[0.2230750273],"iteration":386,"passed_time":0.2016748859,"remaining_time":0.3194488503},
{"learn":[0.2230655851],"iteration":387,"passed_time":0.2020565089,"remaining_time":0.3187076893},
{"learn":[0.2230617204],"iteration":388,"passed_time":0.2024427207,"remaining_time":0.3179755844},
{"learn":[0.2230030741],"iteration":389,"passed_time":0.202832008,"remaining_time":0.3172500638},
{"learn":[0.2229433697],"iteration":390,"passed_time":0.2032252629,"remaining_time":0.3165324427},
{"learn":[0.2228471547],"iteration":391,"passed_time":0.2036188285,"remaining_time":0.3158169585},
{"learn":[0.2226079145],"iteration":392,"passed_time":0.2040283742,"remaining_time":0.3151277943},
{"learn":[0.2225200042],"iteration":393,"passed_time":0.2044295343,"remaining_time":0.3144271517},
{"learn":[0.2223483253],"iteration":394,"passed_time":0.2048469251,"remaining_time":0.3137528852},
{"learn":[0.2221805814],"iteration":395,"passed_time":0.2052620516,"remaining_time":0.3130764625},
{"learn":[0.2221023521],"iteration":396,"passed_time":0.2056659368,"remaining_time":0.3123842818},
{"learn":[0.2220193421],"iteration":397,"passed_time":0.2060807427,"remaining_time":0.3117100681},
{"learn":[0.2217654053],"iteration":398,"passed_time":0.2064794381,"remaining_time":0.3110128879},
{"learn":[0.2216032921],"iteration":399,"passed_time":0.206898472,"remaining_time":0.3103477079},
{"learn":[0.2213174677],"iteration":400,"passed_time":0.2073002033,"remaining_time":0.3096579097},
{"learn":[0.2212017122],"iteration":401,"passed_time":0.2076906733,"remaining_time":0.3089527926},
{"learn":[0.221005252],"iteration":402,"passed_time":0.2081060402,"remaining_time":0.3082861192},
{"learn":[0.2208733304],"iteration":403,"passed_time":0.208504525,"remaining_time":0.3075957844},
{"learn":[0.2207511624],"iteration":404,"passed_time":0.2089109751,"remaining_time":0.306918593},
{"learn":[0.220638139],"iteration":405,"passed_time":0.209328556,"remaining_time":0.3062590204},
{"learn":[0.2205329486],"iteration":406,"passed_time":0.2097369698,"remaining_time":0.3055872803},
{"learn":[0.2204300298],"iteration":407,"passed_time":0.2101354947,"remaining_time":0.3049024824},
{"learn":[0.220347033],"iteration":408,"passed_time":0.2105448502,"remaining_time":0.3042347347},
{"learn":[0.2202752746],"iteration":409,"passed_time":0.2109612191,"remaining_time":0.3035783397},
{"learn":[0.2201780063],"iteration":410,"passed_time":0.2113511579,"remaining_time":0.302885236},
{"learn":[0.2200784997],"iteration":411,"passed_time":0.2117574877,"remaining_time":0.302216997},
{"learn":[0.2198800582],"iteration":412,"passed_time":0.2121492499,"remaining_time":0.3015293213},
{"learn":[0.2197352737],"iteration":413,"passed_time":0.2125604392,"remaining_time":0.3008705733},
{"learn":[0.2196176609],"iteration":414,"passed_time":0.2129571107,"remaining_time":0.3001925537},
{"learn":[0.2194764871],"iteration":415,"passed_time":0.2133413387,"remaining_time":0.2994984178},
{"learn":[0.2194175133],"iteration":416,"passed_time":0.213733642,"remaining_time":0.2988170582},
{"learn":[0.219248568],"iteration":417,"passed_time":0.2141343612,"remaining_time":0.2981487995},
{"learn":[0.2190848349],"iteration":418,"passed_time":0.2145542567,"remaining_time":0.2975084085},
{"learn":[0.219042454],"iteration":419,"passed_time":0.2149401478,"remaining_time":0.2968221089},
{"learn":[0.2189201644],"iteration":420,"passed_time":0.2153396447,"remaining_time":0.2961559484},
{"learn":[0.2189025568],"iteration":421,"passed_time":0.2157258667,"remaining_time":0.2954728695},
{"learn":[0.2187678343],"iteration":422,"passed_time":0.2161160659,"remaining_time":0.2947966195},
{"learn":[0.218691054],"iteration":423,"passed_time":0.2165203118,"remaining_time":0.294140801},
{"learn":[0.2183851204],"iteration":424,"passed_time":0.2169292466,"remaining_time":0.2934925101},
{"learn":[0.2182150118],"iteration":425,"passed_time":0.2173390831,"remaining_time":0.2928465579},
{"learn":[0.2181784464],"iteration":426,"passed_time":0.2177170191,"remaining_time":0.2921589039},
{"learn":[0.2179797411],"iteration":427,"passed_time":0.2181304023,"remaining_time":0.2915200704},
{"learn":[0.2177214129],"iteration":428,"passed_time":0.2185370127,"remaining_time":0.2908732733},
{"learn":[0.2177002133],"iteration":429,"passed_time":0.2189081657,"remaining_time":0.2901805917},
{"learn":[0.2176147826],"iteration":430,"passed_time":0.2193093257,"remaining_time":0.289529017},
{"learn":[0.217510601],"iteration":431,"passed_time":0.2197243721,"remaining_time":0.2888968596},
{"learn":[0.2173765232],"iteration":432,"passed_time":0.2201244198,"remaining_time":0.2882460647},
{"learn":[0.217126575],"iteration":433,"passed_time":0.2205252993,"remaining_time":0.2875975102},
{"learn":[0.2169608126],"iteration":434,"passed_time":0.2209132646,"remaining_time":0.2869333206},
{"learn":[0.2167539069],"iteration":435,"passed_time":0.2213159675,"remaining_time":0.2862894626},
{"learn":[0.2166746036],"iteration":436,"passed_time":0.2216994942,"remaining_time":0.2856220028},
{"learn":[0.2164614367],"iteration":437,"passed_time":0.222108449,"remaining_time":0.2849884665},
{"learn":[0.2164545933],"iteration":438,"passed_time":0.2224864652,"remaining_time":0.2843164168},
{"learn":[0.2163307829],"iteration":439,"passed_time":0.2228890381,"remaining_time":0.2836769576},
{"learn":[0.2163127203],"iteration":440,"passed_time":0.223251695,"remaining_time":0.2829879762},
{"learn":[0.2161897325],"iteration":441,"passed_time":0.2236423952,"remaining_time":0.2823358745},
{"learn":[0.2161716046],"iteration":442,"passed_time":0.2240309714,"remaining_time":0.2816822823},
{"learn":[0.2160735669],"iteration":443,"passed_time":0.224430849,"remaining_time":0.2810440362},
{"learn":[0.2160667869],"iteration":444,"passed_time":0.2248290937,"remaining_time":0.2804048248},
{"learn":[0.2159728923],"iteration":445,"passed_time":0.2252136922,"remaining_time":0.2797497432},
{"learn":[0.2159280653],"iteration":446,"passed_time":0.2256082998,"remaining_time":0.2791082546},
{"learn":[0.2157398529],"iteration":447,"passed_time":0.2260109026,"remaining_time":0.2784777193},
{"learn":[0.2156145655],"iteration":448,"passed_time":0.2264019136,"remaining_time":0.2778339742},
{"learn":[0.215453263],"iteration":449,"passed_time":0.2268241336,"remaining_time":0.2772294966},
{"learn":[0.21532326],"iteration":450,"passed_time":0.2272178297,"remaining_time":0.2765911053},
{"learn":[0.2152356478],"iteration":451,"passed_time":0.2276247108,"remaining_time":0.2759697821},
{"learn":[0.2152292294],"iteration":452,"passed_time":0.2279851336,"remaining_time":0.275293307},
{"learn":[0.2152250094],"iteration":453,"passed_time":0.2283479811,"remaining_time":0.2746211402},
{"learn":[0.2149774739],"iteration":454,"passed_time":0.2287689484,"remaining_time":0.2740199492},
{"learn":[0.2148529365],"iteration":455,"passed_time":0.2291795263,"remaining_time":0.2734071542},
{"learn":[0.214766864],"iteration":456,"passed_time":0.2295872789,"remaining_time":0.2727918871},
{"learn":[0.2145867437],"iteration":457,"passed_time":0.2299775783,"remaining_time":0.2721568722},
{"learn":[0.2145738562],"iteration":458,"passed_time":0.2303536607,"remaining_time":0.2715061665},
{"learn":[0.214511674],"iteration":459,"passed_time":0.2307342716,"remaining_time":0.270861971},
{"learn":[0.2144632959],"iteration":460,"passed_time":0.2311137207,"remaining_time":0.2702175606},
{"learn":[0.214375702],"iteration":461,"passed_time":0.2315225953,"remaining_time":0.2696085634},
{"learn":[0.2143146158],"iteration":462,"passed_time":0.2319573488,"remaining_time":0.2690304456},
{"learn":[0.2142102155],"iteration":463,"passed_time":0.2323695698,"remaining_time":0.2684269169},
{"learn":[0.214026627],"iteration":464,"passed_time":0.2327802679,"remaining_time":0.2678224588},
{"learn":[0.2140240784],"iteration":465,"passed_time":0.2332362015,"remaining_time":0.2672706687},
{"learn":[0.2138793724],"iteration":466,"passed_time":0.2336290458,"remaining_time":0.2666472836},
{"learn":[0.2138024321],"iteration":467,"passed_time":0.2340409061,"remaining_time":0.2660465001},
{"learn":[0.2135771484],"iteration":468,"passed_time":0.2344388499,"remaining_time":0.2654307661},
{"learn":[0.213317031],"iteration":469,"passed_time":0.234833267,"remaining_time":0.2648119819},
{"learn":[0.2131892944],"iteration":470,"passed_time":0.2352531825,"remaining_time":0.2642227889},
{"learn":[0.2129797219],"iteration":471,"passed_time":0.2356653434,"remaining_time":0.2636256384},
{"learn":[0.2129755068],"iteration":472,"passed_time":0.2360542304,"remaining_time":0.2630033392},
{"learn":[0.2128397263],"iteration":473,"passed_time":0.2364447806,"remaining_time":0.2623838704},
{"learn":[0.2126770943],"iteration":474,"passed_time":0.2368622413,"remaining_time":0.2617951088},
{"learn":[0.2125502821],"iteration":475,"passed_time":0.2372822268,"remaining_time":0.2612098463},
{"learn":[0.2124661978],"iteration":476,"passed_time":0.2376715947,"remaining_time":0.2605917065},
{"learn":[0.2123139694],"iteration":477,"passed_time":0.2380945061,"remaining_time":0.2600111552},
{"learn":[0.2121143177],"iteration":478,"passed_time":0.2384911875,"remaining_time":0.2594027321},
{"learn":[0.2120455489],"iteration":479,"passed_time":0.2388863762,"remaining_time":0.2587935742},
{"learn":[0.2120214174],"iteration":480,"passed_time":0.2392773971,"remaining_time":0.2581808089},
{"learn":[0.211878105],"iteration":481,"passed_time":0.2396819934,"remaining_time":0.2575835531},
{"learn":[0.2118121703],"iteration":482,"passed_time":0.2400637064,"remaining_time":0.2569626008},
{"learn":[0.2118090025],"iteration":483,"passed_time":0.2404151322,"remaining_time":0.2563103476},
{"learn":[0.2117421265],"iteration":484,"passed_time":0.2408103111,"remaining_time":0.2557057943},
{"learn":[0.2117214038],"iteration":485,"passed_time":0.2411789896,"remaining_time":0.2550740755},
{"learn":[0.2114387433],"iteration":486,"passed_time":0.2415911906,"remaining_time":0.2544892829},
{"learn":[0.2113065428],"iteration":487,"passed_time":0.241986219,"remaining_time":0.2538871806},
{"learn":[0.2112692479],"iteration":488,"passed_time":0.242402628,"remaining_time":0.2533082677},
{"learn":[0.2110739207],"iteration":489,"passed_time":0.242817624,"remaining_time":0.2527285474},
{"learn":[0.2110694979],"iteration":490,"passed_time":0.2431842484,"remaining_time":0.2520993532},
{"learn":[0.2109420752],"iteration":491,"passed_time":0.2436071496,"remaining_time":0.2515293334},
{"learn":[0.2108079965],"iteration":492,"passed_time":0.2440045025,"remaining_time":0.2509336364},
{"learn":[0.2106765471],"iteration":493,"passed_time":0.2444278347,"remaining_time":0.250365353},
{"learn":[0.210527459],"iteration":494,"passed_time":0.2448338939,"remaining_time":0.2497800331},
{"learn":[0.2104172743],"iteration":495,"passed_time":0.2452435901,"remaining_time":0.2491991318},
{"learn":[0.2101833797],"iteration":496,"passed_time":0.2456469044,"remaining_time":0.2486124606},
{"learn":[0.2100954611],"iteration":497,"passed_time":0.2460429948,"remaining_time":0.2480192438},
{"learn":[0.2098831705],"iteration":498,"passed_time":0.2464624598,"remaining_time":0.2474502853},
{"learn":[0.2097479783],"iteration":499,"passed_time":0.2468656935,"remaining_time":0.2468656935},
{"learn":[0.2095722275],"iteration":500,"passed_time":0.247276592,"remaining_time":0.2462894599},
{"learn":[0.2093477958],"iteration":501,"passed_time":0.2476916085,"remaining_time":0.2457179702},
{"learn":[0.2093224418],"iteration":502,"passed_time":0.2480901334,"remaining_time":0.2451308077},
{"learn":[0.2090812111],"iteration":503,"passed_time":0.2484856529,"remaining_time":0.2445414362},
{"learn":[0.2089089157],"iteration":504,"passed_time":0.2488764832,"remaining_time":0.243948236},
{"learn":[0.2089065568],"iteration":505,"passed_time":0.249254299,"remaining_time":0.2433431299},
{"learn":[0.2087784416],"iteration":506,"passed_time":0.2496487664,"remaining_time":0.2427551121},
{"learn":[0.2085431134],"iteration":507,"passed_time":0.2500656963,"remaining_time":0.2421896114},
{"learn":[0.2084471175],"iteration":508,"passed_time":0.2504555148,"remaining_time":0.2415985418},
{"learn":[0.2082811308],"iteration":509,"passed_time":0.2508854592,"remaining_time":0.2410468138},
{"learn":[0.2081853762],"iteration":510,"passed_time":0.2512846658,"remaining_time":0.2404661479},
{"learn":[0.2080422458],"iteration":511,"passed_time":0.251675366,"remaining_time":0.2398780832},
{"learn":[0.2079481631],"iteration":512,"passed_time":0.2523021736,"remaining_time":0.2395149289},
{"learn":[0.2079442377],"iteration":513,"passed_time":0.2526725254,"remaining_time":0.2389082633},
{"learn":[0.2078802552],"iteration":514,"passed_time":0.2530870107,"remaining_time":0.2383440781},
{"learn":[0.2077105774],"iteration":515,"passed_time":0.2534826301,"remaining_time":0.237762777},
{"learn":[0.2074806081],"iteration":516,"passed_time":0.2538965543,"remaining_time":0.2371992954},
{"learn":[0.2074225398],"iteration":517,"passed_time":0.2542827259,"remaining_time":0.2366105674},
{"learn":[0.2074194157],"iteration":518,"passed_time":0.2546692685,"remaining_time":0.2360229637},
{"learn":[0.2073186667],"iteration":519,"passed_time":0.2550616319,"remaining_time":0.2354415063},
{"learn":[0.2071929098],"iteration":520,"passed_time":0.2554657677,"remaining_time":0.2348715984},
{"learn":[0.2069612405],"iteration":521,"passed_time":0.2558946403,"remaining_time":0.2343249771},
{"learn":[0.2069502833],"iteration":522,"passed_time":0.2562768645,"remaining_time":0.2337362607},
{"learn":[0.206870147],"iteration":523,"passed_time":0.2566906182,"remaining_time":0.2331769737},
{"learn":[0.2066741068],"iteration":524,"passed_time":0.2570905158,"remaining_time":0.2326057048},
{"learn":[0.2066027418],"iteration":525,"passed_time":0.2574943311,"remaining_time":0.2320386177},
{"learn":[0.2064861845],"iteration":526,"passed_time":0.257884851,"remaining_time":0.2314602173},
{"learn":[0.2063692058],"iteration":527,"passed_time":0.2582688888,"remaining_time":0.2308767339},
{"learn":[0.2061476869],"iteration":528,"passed_time":0.2587033319,"remaining_time":0.2303388834},
{"learn":[0.2061437687],"iteration":529,"passed_time":0.2590764388,"remaining_time":0.2297470306},
{"learn":[0.2060768014],"iteration":530,"passed_time":0.25948349,"remaining_time":0.2291859827},
{"learn":[0.2059674121],"iteration":531,"passed_time":0.2598892485,"remaining_time":0.2286243765},
{"learn":[0.2058043603],"iteration":532,"passed_time":0.2602915409,"remaining_time":0.2280603182},
{"learn":[0.205631405],"iteration":533,"passed_time":0.2607083506,"remaining_time":0.2275095344},
{"learn":[0.2055195473],"iteration":534,"passed_time":0.2611098411,"remaining_time":0.2269459366},
{"learn":[0.2054226719],"iteration":535,"passed_time":0.2615231241,"remaining_time":0.2263931522},
{"learn":[0.2053227149],"iteration":536,"passed_time":0.2619253964,"remaining_time":0.2258313939},
{"learn":[0.2051844599],"iteration":537,"passed_time":0.2623413948,"remaining_time":0.2252820156},
{"learn":[0.2050670203],"iteration":538,"passed_time":0.262751071,"remaining_time":0.2247277249},
{"learn":[0.2050599119],"iteration":539,"passed_time":0.2631534734,"remaining_time":0.2241677736},
{"learn":[0.2047771776],"iteration":540,"passed_time":0.2635371701,"remaining_time":0.2235925344},
{"learn":[0.2047527935],"iteration":541,"passed_time":0.2639215682,"remaining_time":0.2230185945},
{"learn":[0.2046062105],"iteration":542,"passed_time":0.2643358331,"remaining_time":0.2224704893},
{"learn":[0.2045924987],"iteration":543,"passed_time":0.2647078677,"remaining_time":0.2218874774},
{"learn":[0.2044493197],"iteration":544,"passed_time":0.2651152796,"remaining_time":0.2213347747},
{"learn":[0.2044442036],"iteration":545,"passed_time":0.2654852005,"remaining_time":0.2207514304},
{"learn":[0.2043702246],"iteration":546,"passed_time":0.2659032627,"remaining_time":0.220208735},
{"learn":[0.2043531799],"iteration":547,"passed_time":0.2663015071,"remaining_time":0.2196501482},
{"learn":[0.2042102213],"iteration":548,"passed_time":0.2666982187,"remaining_time":0.2190908864},
{"learn":[0.204190987],"iteration":549,"passed_time":0.2670888187,"remaining_time":0.2185272153},
{"learn":[0.204090265],"iteration":550,"passed_time":0.2674772048,"remaining_time":0.2179623683},
{"learn":[0.2038870075],"iteration":551,"passed_time":0.2678908382,"remaining_time":0.2174186513},
{"learn":[0.2037799314],"iteration":552,"passed_time":0.268290255,"remaining_time":0.2168639131},
{"learn":[0.2037224177],"iteration":553,"passed_time":0.2687187668,"remaining_time":0.2163331589},
{"learn":[0.2035818276],"iteration":554,"passed_time":0.2691093771,"remaining_time":0.2157723834},
{"learn":[0.2034018531],"iteration":555,"passed_time":0.2695007987,"remaining_time":0.215212868},
{"learn":[0.2031557122],"iteration":556,"passed_time":0.269922247,"remaining_time":0.2146778373},
{"learn":[0.2029802149],"iteration":557,"passed_time":0.2703219741,"remaining_time":0.2141260081},
{"learn":[0.2027205678],"iteration":558,"passed_time":0.2707398458,"remaining_time":0.2135890376},
{"learn":[0.2026285623],"iteration":559,"passed_time":0.2711574267,"remaining_time":0.2130522639},
{"learn":[0.2025322296],"iteration":560,"passed_time":0.271579176,"remaining_time":0.2125191769},
{"learn":[0.202484702],"iteration":561,"passed_time":0.2719662493,"remaining_time":0.2119594612},
{"learn":[0.2024258743],"iteration":562,"passed_time":0.2723572403,"remaining_time":0.2114033997},
{"learn":[0.2024220383],"iteration":563,"passed_time":0.2727268606,"remaining_time":0.2108314029},
{"learn":[0.2022897516],"iteration":564,"passed_time":0.2731179518,"remaining_time":0.2102766531},
{"learn":[0.2021931729],"iteration":565,"passed_time":0.2735367551,"remaining_time":0.2097437309},
{"learn":[0.202135776],"iteration":566,"passed_time":0.2739365427,"remaining_time":0.2091966896},
{"learn":[0.201971483],"iteration":567,"passed_time":0.274369954,"remaining_time":0.2086757397},
{"learn":[0.2018587339],"iteration":568,"passed_time":0.274770663,"remaining_time":0.2081303265},
{"learn":[0.201713994],"iteration":569,"passed_time":0.2751603315,"remaining_time":0.2075770922},
{"learn":[0.2016732931],"iteration":570,"passed_time":0.2755493485,"remaining_time":0.2070239414},
{"learn":[0.2015182926],"iteration":571,"passed_time":0.2759454087,"remaining_time":0.2064766345},
{"learn":[0.2013751755],"iteration":572,"passed_time":0.2763772068,"remaining_time":0.2059564874},
{"learn":[0.2013707852],"iteration":573,"passed_time":0.2767442622,"remaining_time":0.2053885988},
{"learn":[0.201242212],"iteration":574,"passed_time":0.2771572946,"remaining_time":0.2048553916},
{"learn":[0.2010742886],"iteration":575,"passed_time":0.2776256018,"remaining_time":0.2043632902},
{"learn":[0.2008981861],"iteration":576,"passed_time":0.2780664869,"remaining_time":0.2038511681},
{"learn":[0.2006933251],"iteration":577,"passed_time":0.278478097,"remaining_time":0.2033179186},
{"learn":[0.2006346167],"iteration":578,"passed_time":0.2788716626,"remaining_time":0.2027719689},
{"learn":[0.2004780042],"iteration":579,"passed_time":0.2793056747,"remaining_time":0.2022558334},
{"learn":[0.2003174007],"iteration":580,"passed_time":0.2797087584,"remaining_time":0.201717676},
{"learn":[0.2001499266],"iteration":581,"passed_time":0.2801188554,"remaining_time":0.2011850198},
{"learn":[0.2000339915],"iteration":582,"passed_time":0.2805301346,"remaining_time":0.2006536297},
{"learn":[0.1998345882],"iteration":583,"passed_time":0.2809427862,"remaining_time":0.2001236285},
{"learn":[0.1996043495],"iteration":584,"passed_time":0.2813581033,"remaining_time":0.1995959194},
{"learn":[0.1994718309],"iteration":585,"passed_time":0.2817831886,"remaining_time":0.199075495},
{"learn":[0.1994683446],"iteration":586,"passed_time":0.2821649519,"remaining_time":0.1985249151},
{"learn":[0.1993425716],"iteration":587,"passed_time":0.2825626654,"remaining_time":0.1979860853},
{"learn":[0.1991198769],"iteration":588,"passed_time":0.2829893338,"remaining_time":0.1974679392},
{"learn":[0.1990825863],"iteration":589,"passed_time":0.2833799539,"remaining_time":0.1969250527},
{"learn":[0.1989502963],"iteration":590,"passed_time":0.2837866043,"remaining_time":0.1963937753},
{"learn":[0.1987937182],"iteration":591,"passed_time":0.2841892169,"remaining_time":0.195860136},
{"learn":[0.1985730744],"iteration":592,"passed_time":0.2846071688,"remaining_time":0.1953374666},
{"learn":[0.1984716233],"iteration":593,"passed_time":0.2850134082,"remaining_time":0.1948071444},
{"learn":[0.1982915547],"iteration":594,"passed_time":0.2854051304,"remaining_time":0.1942673577},
{"learn":[0.1980118742],"iteration":595,"passed_time":0.2858517664,"remaining_time":0.1937652913},
{"learn":[0.1980071012],"iteration":596,"passed_time":0.2862214468,"remaining_time":0.1932114624},
{"learn":[0.1977811294],"iteration":597,"passed_time":0.2866495277,"remaining_time":0.1926975086},
{"learn":[0.1976516682],"iteration":598,"passed_time":0.287040398,"remaining_time":0.1921589309},
{"learn":[0.19743069],"iteration":599,"passed_time":0.2874639004,"remaining_time":0.1916426002},
{"learn":[0.1973115203],"iteration":600,"passed_time":0.2878603617,"remaining_time":0.1911086262},
{"learn":[0.1972109238],"iteration":601,"passed_time":0.2882494389,"remaining_time":0.190570227},
{"learn":[0.1970184766],"iteration":602,"passed_time":0.2886661684,"remaining_time":0.1900505288},
{"learn":[0.1969333341],"iteration":603,"passed_time":0.2890614373,"remaining_time":0.1895171013},
{"learn":[0.1969285758],"iteration":604,"passed_time":0.2894400648,"remaining_time":0.1889732655},
{"learn":[0.1968225187],"iteration":605,"passed_time":0.2898399527,"remaining_time":0.1884437976},
{"learn":[0.1966896205],"iteration":606,"passed_time":0.290267102,"remaining_time":0.187932407},
{"learn":[0.196687268],"iteration":607,"passed_time":0.290629819,"remaining_time":0.1873797517},
{"learn":[0.1966850939],"iteration":608,"passed_time":0.2909841503,"remaining_time":0.1868223362},
{"learn":[0.1965753798],"iteration":609,"passed_time":0.2913764936,"remaining_time":0.1862898894},
{"learn":[0.196384968],"iteration":610,"passed_time":0.2917835048,"remaining_time":0.1857672395},
{"learn":[0.1963746517],"iteration":611,"passed_time":0.2921759381,"remaining_time":0.1852357254},
{"learn":[0.1963592415],"iteration":612,"passed_time":0.2925566594,"remaining_time":0.1846972711},
{"learn":[0.1963392835],"iteration":613,"passed_time":0.2929432817,"remaining_time":0.1841630403},
{"learn":[0.1960959933],"iteration":614,"passed_time":0.2933477279,"remaining_time":0.1836404476},
{"learn":[0.1959347096],"iteration":615,"passed_time":0.2937522241,"remaining_time":0.1831182696},
{"learn":[0.1958965773],"iteration":616,"passed_time":0.2941622507,"remaining_time":0.182599906},
{"learn":[0.1957757861],"iteration":617,"passed_time":0.2945674384,"remaining_time":0.1820789021},
{"learn":[0.1956193694],"iteration":618,"passed_time":0.2949816231,"remaining_time":0.18156381},
{"learn":[0.1955203744],"iteration":619,"passed_time":0.2953794466,"remaining_time":0.1810390157},
{"learn":[0.1954154272],"iteration":620,"passed_time":0.2957880907,"remaining_time":0.1805212341},
{"learn":[0.1953224416],"iteration":621,"passed_time":0.2961780294,"remaining_time":0.1799924359},
{"learn":[0.1951844711],"iteration":622,"passed_time":0.2965775566,"remaining_time":0.1794698858},
{"learn":[0.1950404136],"iteration":623,"passed_time":0.2969992155,"remaining_time":0.1789610657},
{"learn":[0.1948827613],"iteration":624,"passed_time":0.297394284,"remaining_time":0.1784365704},
{"learn":[0.1947555039],"iteration":625,"passed_time":0.297814981,"remaining_time":0.1779278002},
{"learn":[0.1946656421],"iteration":626,"passed_time":0.2982015334,"remaining_time":0.1773989983},
{"learn":[0.1945299402],"iteration":627,"passed_time":0.2986174712,"remaining_time":0.1768880562},
{"learn":[0.1944426702],"iteration":628,"passed_time":0.2990077707,"remaining_time":0.176362294},
{"learn":[0.1943388865],"iteration":629,"passed_time":0.2994078589,"remaining_time":0.1758427108},
{"learn":[0.1942245051],"iteration":630,"passed_time":0.2998257106,"remaining_time":0.1753338941},
{"learn":[0.1942028598],"iteration":631,"passed_time":0.3002070032,"remaining_time":0.1748040778},
{"learn":[0.1940341845],"iteration":632,"passed_time":0.3006278806,"remaining_time":0.1742976812},
{"learn":[0.1938242207],"iteration":633,"passed_time":0.3010232096,"remaining_time":0.1737768055},
{"learn":[0.1937754371],"iteration":634,"passed_time":0.3014397886,"remaining_time":0.1732685399},
{"learn":[0.1937063377],"iteration":635,"passed_time":0.301837332,"remaining_time":0.172749668},
{"learn":[0.193606538],"iteration":636,"passed_time":0.3022378206,"remaining_time":0.1722328554},
{"learn":[0.1935382749],"iteration":637,"passed_time":0.3026638478,"remaining_time":0.1717308979},
{"learn":[0.1934248878],"iteration":638,"passed_time":0.3030599382,"remaining_time":0.1712122656},
{"learn":[0.1933528709],"iteration":639,"passed_time":0.3034916263,"remaining_time":0.1707140398},
{"learn":[0.1932880976],"iteration":640,"passed_time":0.3038797318,"remaining_time":0.1701916127},
{"learn":[0.1931673397],"iteration":641,"passed_time":0.3043064701,"remaining_time":0.1696911469},
{"learn":[0.1930695579],"iteration":642,"passed_time":0.3047243618,"remaining_time":0.1691859987},
{"learn":[0.1928957079],"iteration":643,"passed_time":0.3051426143,"remaining_time":0.1686813209},
{"learn":[0.192893526],"iteration":644,"passed_time":0.3055003921,"remaining_time":0.1681436267},
{"learn":[0.1927659409],"iteration":645,"passed_time":0.3058951298,"remaining_time":0.1676267429},
{"learn":[0.1925926933],"iteration":646,"passed_time":0.3063125206,"remaining_time":0.1671225962},
{"learn":[0.1924604431],"iteration":647,"passed_time":0.3067186398,"remaining_time":0.1666125945},
{"learn":[0.1922743261],"iteration":648,"passed_time":0.3071344276,"remaining_time":0.1661081419},
{"learn":[0.1921561136],"iteration":649,"passed_time":0.3075342651,"remaining_time":0.1655953735},
{"learn":[0.1920456278],"iteration":650,"passed_time":0.3079448532,"remaining_time":0.1650887155},
{"learn":[0.1918955525],"iteration":651,"passed_time":0.3083480772,"remaining_time":0.1645784216},
{"learn":[0.1917913244],"iteration":652,"passed_time":0.3087539564,"remaining_time":0.1640698665},
{"learn":[0.191644327],"iteration":653,"passed_time":0.3091719381,"remaining_time":0.1635680284},
{"learn":[0.1915495926],"iteration":654,"passed_time":0.3095768354,"remaining_time":0.1630595545},
{"learn":[0.1913930395],"iteration":655,"passed_time":0.309989788,"remaining_time":0.1625556205},
{"learn":[0.1912761053],"iteration":656,"passed_time":0.310384095,"remaining_time":0.1620422292},
{"learn":[0.1911840675],"iteration":657,"passed_time":0.3107933807,"remaining_time":0.1615369851},
{"learn":[0.1910673954],"iteration":658,"passed_time":0.3111912946,"remaining_time":0.1610261479},
{"learn":[0.1909287102],"iteration":659,"passed_time":0.3115970433,"remaining_time":0.160519689},
{"learn":[0.1907936911],"iteration":660,"passed_time":0.3120142738,"remaining_time":0.1600194233},
{"learn":[0.1907593135],"iteration":661,"passed_time":0.3124007759,"remaining_time":0.1595037194},
{"learn":[0.1906830077],"iteration":662,"passed_time":0.3128158525,"remaining_time":0.1590029295},
{"learn":[0.1905188625],"iteration":663,"passed_time":0.313221912,"remaining_time":0.158497835},
{"learn":[0.190510278],"iteration":664,"passed_time":0.3136170206,"remaining_time":0.1579875217},
{"learn":[0.1904221821],"iteration":665,"passed_time":0.3140053064,"remaining_time":0.1574741327},
{"learn":[0.1903375827],"iteration":666,"passed_time":0.3144244107,"remaining_time":0.1569765049},
{"learn":[0.190255413],"iteration":667,"passed_time":0.3148387255,"remaining_time":0.1564767318},
{"learn":[0.1901138071],"iteration":668,"passed_time":0.3152306378,"remaining_time":0.1559661302},
{"learn":[0.1900330122],"iteration":669,"passed_time":0.3156293532,"remaining_time":0.1554592337},
{"learn":[0.1899761278],"iteration":670,"passed_time":0.3160199029,"remaining_time":0.1549486558},
{"learn":[0.1899724379],"iteration":671,"passed_time":0.316389333,"remaining_time":0.1544281268},
{"learn":[0.1898704345],"iteration":672,"passed_time":0.3167778291,"remaining_time":0.1539173107},
{"learn":[0.1897066696],"iteration":673,"passed_time":0.3171766144,"remaining_time":0.1534118343},
{"learn":[0.1897048958],"iteration":674,"passed_time":0.317556394,"remaining_time":0.152897523},
{"learn":[0.1895980479],"iteration":675,"passed_time":0.3179614111,"remaining_time":0.1523957059},
{"learn":[0.1894268451],"iteration":676,"passed_time":0.3183930088,"remaining_time":0.1519068565},
{"learn":[0.1893557885],"iteration":677,"passed_time":0.3188072136,"remaining_time":0.1514099156},
{"learn":[0.1892655367],"iteration":678,"passed_time":0.3192190841,"remaining_time":0.1509121149},
{"learn":[0.1892620255],"iteration":679,"passed_time":0.319597481,"remaining_time":0.1503988146},
{"learn":[0.1890575366],"iteration":680,"passed_time":0.3199876803,"remaining_time":0.1498914391},
{"learn":[0.1889940928],"iteration":681,"passed_time":0.3203977871,"remaining_time":0.1493936896},
{"learn":[0.1888875569],"iteration":682,"passed_time":0.3207912926,"remaining_time":0.1488884916},
{"learn":[0.1888584609],"iteration":683,"passed_time":0.3211913105,"remaining_time":0.1483866288},
{"learn":[0.1887462322],"iteration":684,"passed_time":0.3215835038,"remaining_time":0.1478814652},
{"learn":[0.1886399142],"iteration":685,"passed_time":0.3219878699,"remaining_time":0.1473822028},
{"learn":[0.188585004],"iteration":686,"passed_time":0.32238894,"remaining_time":0.146881715},
{"learn":[0.1885431015],"iteration":687,"passed_time":0.3227977545,"remaining_time":0.1463850282},
{"learn":[0.1885209273],"iteration":688,"passed_time":0.3231963399,"remaining_time":0.1458839793},
{"learn":[0.1884077692],"iteration":689,"passed_time":0.3236095325,"remaining_time":0.14538979},
{"learn":[0.1883433405],"iteration":690,"passed_time":0.3240355396,"remaining_time":0.1449015655},
{"learn":[0.1883002489],"iteration":691,"passed_time":0.3244316002,"remaining_time":0.144400192},
{"learn":[0.1880841246],"iteration":692,"passed_time":0.3248503937,"remaining_time":0.1439091932},
{"learn":[0.1880823323],"iteration":693,"passed_time":0.3252293917,"remaining_time":0.1434008557},
{"learn":[0.187997293],"iteration":694,"passed_time":0.3256252217,"remaining_time":0.1429002771},
{"learn":[0.1878667996],"iteration":695,"passed_time":0.3260595846,"remaining_time":0.1424168301},
{"learn":[0.1877186107],"iteration":696,"passed_time":0.3264650528,"remaining_time":0.1419209627},
{"learn":[0.1876428356],"iteration":697,"passed_time":0.3268854796,"remaining_time":0.1414318264},
{"learn":[0.1875364756],"iteration":698,"passed_time":0.3272984821,"remaining_time":0.1409396897},
{"learn":[0.1874417413],"iteration":699,"passed_time":0.327710232,"remaining_time":0.1404472423},
{"learn":[0.1873298034],"iteration":700,"passed_time":0.3281167123,"remaining_time":0.1399527774},
{"learn":[0.1871380361],"iteration":701,"passed_time":0.3285106685,"remaining_time":0.1394532467},
{"learn":[0.1870686699],"iteration":702,"passed_time":0.3289044848,"remaining_time":0.1389539573},
{"learn":[0.1869166225],"iteration":703,"passed_time":0.3293188699,"remaining_time":0.1384636158},
{"learn":[0.1866809172],"iteration":704,"passed_time":0.3297377734,"remaining_time":0.1379753803},
{"learn":[0.1866783769],"iteration":705,"passed_time":0.3301146372,"remaining_time":0.1374698347},
{"learn":[0.1865818445],"iteration":706,"passed_time":0.3305282306,"remaining_time":0.1369798749},
{"learn":[0.1863768529],"iteration":707,"passed_time":0.330930523,"remaining_time":0.1364854699},
{"learn":[0.186303468],"iteration":708,"passed_time":0.3313315828,"remaining_time":0.1359908189},
{"learn":[0.1862459862],"iteration":709,"passed_time":0.3317302079,"remaining_time":0.135495437},
{"learn":[0.1861691071],"iteration":710,"passed_time":0.3321339225,"remaining_time":0.1350023961},
{"learn":[0.1861074666],"iteration":711,"passed_time":0.3325455322,"remaining_time":0.1345127995},
{"learn":[0.1859617817],"iteration":712,"passed_time":0.3329533146,"remaining_time":0.1340218812},
{"learn":[0.1858436195],"iteration":713,"passed_time":0.33338898,"remaining_time":0.1335423645},
{"learn":[0.1857726449],"iteration":714,"passed_time":0.3338090959,"remaining_time":0.1330567725},
{"learn":[0.185622059],"iteration":715,"passed_time":0.3342288614,"remaining_time":0.1325712244},
{"learn":[0.185483808],"iteration":716,"passed_time":0.3346370045,"remaining_time":0.1320812723},
{"learn":[0.1853475554],"iteration":717,"passed_time":0.3350360704,"remaining_time":0.1315879831},
{"learn":[0.185333971],"iteration":718,"passed_time":0.3354207993,"remaining_time":0.1310893527},
{"learn":[0.1852481834],"iteration":719,"passed_time":0.3358243438,"remaining_time":0.1305983559},
{"learn":[0.1851016959],"iteration":720,"passed_time":0.3362355928,"remaining_time":0.1301105831},
{"learn":[0.1850986725],"iteration":721,"passed_time":0.3366061949,"remaining_time":0.1296073715},
{"learn":[0.1848340809],"iteration":722,"passed_time":0.3370088578,"remaining_time":0.12911681},
{"learn":[0.184740046],"iteration":723,"passed_time":0.3374178126,"remaining_time":0.1286288899},
{"learn":[0.1845837518],"iteration":724,"passed_time":0.3378070501,"remaining_time":0.1281337087},
{"learn":[0.1844686828],"iteration":725,"passed_time":0.3382197021,"remaining_time":0.1276476562},
{"learn":[0.1844519583],"iteration":726,"passed_time":0.3385965361,"remaining_time":0.1271483554},
{"learn":[0.1844248935],"iteration":727,"passed_time":0.33899436,"remaining_time":0.1266572334},
{"learn":[0.184422136],"iteration":728,"passed_time":0.3393537008,"remaining_time":0.1261520616},
{"learn":[0.1843214886],"iteration":729,"passed_time":0.3397524162,"remaining_time":0.1256618526},
{"learn":[0.1842782127],"iteration":730,"passed_time":0.3401576538,"remaining_time":0.1251742939},
{"learn":[0.184172424],"iteration":731,"passed_time":0.3405388159,"remaining_time":0.1246781457},
{"learn":[0.1841121402],"iteration":732,"passed_time":0.3409547141,"remaining_time":0.1241949641},
{"learn":[0.1838309359],"iteration":733,"passed_time":0.3413697204,"remaining_time":0.1237116425},
{"learn":[0.1838043507],"iteration":734,"passed_time":0.3417788355,"remaining_time":0.1232263829},
{"learn":[0.1836237952],"iteration":735,"passed_time":0.3421854958,"remaining_time":0.1227404496},
{"learn":[0.1835236344],"iteration":736,"passed_time":0.3426086174,"remaining_time":0.1222606057},
{"learn":[0.1834024798],"iteration":737,"passed_time":0.3430037059,"remaining_time":0.1217709634},
{"learn":[0.1832885276],"iteration":738,"passed_time":0.3433914307,"remaining_time":0.1212789762},
{"learn":[0.1831977662],"iteration":739,"passed_time":0.3437993836,"remaining_time":0.120794378},
{"learn":[0.1830766904],"iteration":740,"passed_time":0.3441978488,"remaining_time":0.1203066705},
{"learn":[0.1830737912],"iteration":741,"passed_time":0.3445791009,"remaining_time":0.1198132184},
{"learn":[0.1830417123],"iteration":742,"passed_time":0.3449556543,"remaining_time":0.119318443},
{"learn":[0.1829522928],"iteration":743,"passed_time":0.3454665721,"remaining_time":0.1188702184},
{"learn":[0.18285523],"iteration":744,"passed_time":0.3458759375,"remaining_time":0.1183870659},
{"learn":[0.1827545487],"iteration":745,"passed_time":0.3463104906,"remaining_time":0.1179126872},
{"learn":[0.1826432083],"iteration":746,"passed_time":0.3467168605,"remaining_time":0.1174288698},
{"learn":[0.1824577853],"iteration":747,"passed_time":0.347116568,"remaining_time":0.1169430149},
{"learn":[0.1823245777],"iteration":748,"passed_time":0.3475422746,"remaining_time":0.1164661027},
{"learn":[0.1822959785],"iteration":749,"passed_time":0.3479338867,"remaining_time":0.1159779622},
{"learn":[0.1821790797],"iteration":750,"passed_time":0.348354704,"remaining_time":0.115499762},
{"learn":[0.182070762],"iteration":751,"passed_time":0.3487722551,"remaining_time":0.1150206373},
{"learn":[0.1819046853],"iteration":752,"passed_time":0.3491927718,"remaining_time":0.1145426489},
{"learn":[0.1818435972],"iteration":753,"passed_time":0.3495862774,"remaining_time":0.1140560003},
{"learn":[0.1816352234],"iteration":754,"passed_time":0.3499957932,"remaining_time":0.1135747938},
{"learn":[0.1815542514],"iteration":755,"passed_time":0.3503983457,"remaining_time":0.1130915296},
{"learn":[0.1814664821],"iteration":756,"passed_time":0.35080704,"remaining_time":0.1126104501},
{"learn":[0.1813462396],"iteration":757,"passed_time":0.3512110757,"remaining_time":0.1121280743},
{"learn":[0.1812417212],"iteration":758,"passed_time":0.3516129371,"remaining_time":0.1116452145},
{"learn":[0.1811795565],"iteration":759,"passed_time":0.3520336444,"remaining_time":0.1111685193},
{"learn":[0.1811372222],"iteration":760,"passed_time":0.3524309171,"remaining_time":0.1106846113},
{"learn":[0.1810216666],"iteration":761,"passed_time":0.3528381085,"remaining_time":0.1102040286},
{"learn":[0.1808915208],"iteration":762,"passed_time":0.3532311332,"remaining_time":0.109719238},
{"learn":[0.1807622895],"iteration":763,"passed_time":0.3536313612,"remaining_time":0.1092369126},
{"learn":[0.1806544104],"iteration":764,"passed_time":0.3540300668,"remaining_time":0.1087543343},
{"learn":[0.1804949749],"iteration":765,"passed_time":0.3544374587,"remaining_time":0.1082746284},
{"learn":[0.1803872736],"iteration":766,"passed_time":0.354860921,"remaining_time":0.1077999929},
{"learn":[0.1803423965],"iteration":767,"passed_time":0.3552595865,"remaining_time":0.1073180001},
{"learn":[0.1802914444],"iteration":768,"passed_time":0.3556687617,"remaining_time":0.106839381},
{"learn":[0.1801950068],"iteration":769,"passed_time":0.3560744503,"remaining_time":0.1063599008},
{"learn":[0.1800926124],"iteration":770,"passed_time":0.3564840864,"remaining_time":0.1058817844},
{"learn":[0.1800024267],"iteration":771,"passed_time":0.3569190403,"remaining_time":0.1054113228},
{"learn":[0.1799165241],"iteration":772,"passed_time":0.3573137281,"remaining_time":0.1049291284},
{"learn":[0.1797651065],"iteration":773,"passed_time":0.3577298266,"remaining_time":0.1044534119},
{"learn":[0.1797619788],"iteration":774,"passed_time":0.358097774,"remaining_time":0.1039638699},
{"learn":[0.1797288246],"iteration":775,"passed_time":0.3584939446,"remaining_time":0.1034827881},
{"learn":[0.1796125076],"iteration":776,"passed_time":0.3588979299,"remaining_time":0.1030041678},
{"learn":[0.1796110132],"iteration":777,"passed_time":0.3592615789,"remaining_time":0.1025142295},
{"learn":[0.1795478816],"iteration":778,"passed_time":0.3596610255,"remaining_time":0.102034771},
{"learn":[0.1794809701],"iteration":779,"passed_time":0.3600596007,"remaining_time":0.101555272},
{"learn":[0.1794001684],"iteration":780,"passed_time":0.3604587168,"remaining_time":0.1010761319},
{"learn":[0.1793970744],"iteration":781,"passed_time":0.3608370336,"remaining_time":0.1005913981},
{"learn":[0.1792850682],"iteration":782,"passed_time":0.361251689,"remaining_time":0.100117007},
{"learn":[0.179231991],"iteration":783,"passed_time":0.3616456055,"remaining_time":0.09963705458},
{"learn":[0.1792024157],"iteration":784,"passed_time":0.3620436098,"remaining_time":0.0991584409},
{"learn":[0.179085333],"iteration":785,"passed_time":0.3624843751,"remaining_time":0.09869167464},
{"learn":[0.179021561],"iteration":786,"passed_time":0.3628978887,"remaining_time":0.09821759885},
{"learn":[0.178910856],"iteration":787,"passed_time":0.3633152795,"remaining_time":0.09774471987},
{"learn":[0.1787513526],"iteration":788,"passed_time":0.3637254967,"remaining_time":0.09727006313},
{"learn":[0.178658211],"iteration":789,"passed_time":0.3641403124,"remaining_time":0.09679679191},
{"learn":[0.1785700883],"iteration":790,"passed_time":0.3645451795,"remaining_time":0.09632103984},
{"learn":[0.1784070643],"iteration":791,"passed_time":0.364936651,"remaining_time":0.09584194874},
{"learn":[0.1783498951],"iteration":792,"passed_time":0.3653433918,"remaining_time":0.09536706444},
{"learn":[0.1781787037],"iteration":793,"passed_time":0.3657470766,"remaining_time":0.09489155892},
{"learn":[0.1781087708],"iteration":794,"passed_time":0.366156222,"remaining_time":0.09441764215},
{"learn":[0.1781064528],"iteration":795,"passed_time":0.3665147715,"remaining_time":0.09393092134},
{"learn":[0.1780217699],"iteration":796,"passed_time":0.3669249188,"remaining_time":0.09345766439},
{"learn":[0.1779233368],"iteration":797,"passed_time":0.3673250868,"remaining_time":0.0929820395},
{"learn":[0.1778440973],"iteration":798,"passed_time":0.3677205258,"remaining_time":0.09250541386},
{"learn":[0.1777581654],"iteration":799,"passed_time":0.3681339593,"remaining_time":0.09203348981},
{"learn":[0.1775864348],"iteration":800,"passed_time":0.3685360513,"remaining_time":0.09155889413},
{"learn":[0.1774439259],"iteration":801,"passed_time":0.3689539733,"remaining_time":0.09108838742},
{"learn":[0.1772920671],"iteration":802,"passed_time":0.3693533099,"remaining_time":0.09061345211},
{"learn":[0.1772136097],"iteration":803,"passed_time":0.3697623248,"remaining_time":0.09014106425},
{"learn":[0.1770157786],"iteration":804,"passed_time":0.3701677529,"remaining_time":0.08966796499},
{"learn":[0.1769363867],"iteration":805,"passed_time":0.3705728204,"remaining_time":0.08919494684},
{"learn":[0.1768605797],"iteration":806,"passed_time":0.3709857529,"remaining_time":0.08872397808},
{"learn":[0.1767556313],"iteration":807,"passed_time":0.3713903595,"remaining_time":0.08825117453},
{"learn":[0.1766237921],"iteration":808,"passed_time":0.3718088826,"remaining_time":0.08778182519},
{"learn":[0.1764339405],"iteration":809,"passed_time":0.3722209932,"remaining_time":0.08731109717},
{"learn":[0.1763757733],"iteration":810,"passed_time":0.3726320618,"remaining_time":0.08684027088},
{"learn":[0.1762554557],"iteration":811,"passed_time":0.3730296449,"remaining_time":0.0863664695},
{"learn":[0.1760493764],"iteration":812,"passed_time":0.3734511938,"remaining_time":0.08589836806},
{"learn":[0.1759657965],"iteration":813,"passed_time":0.3738339487,"remaining_time":0.08542151654},
{"learn":[0.1759200559],"iteration":814,"passed_time":0.3742208417,"remaining_time":0.08494583524},
{"learn":[0.1757940821],"iteration":815,"passed_time":0.3746340548,"remaining_time":0.08447630648},
{"learn":[0.175782342],"iteration":816,"passed_time":0.3750142253,"remaining_time":0.08399951436},
{"learn":[0.1755502985],"iteration":817,"passed_time":0.3754449614,"remaining_time":0.08353420901},
{"learn":[0.175547079],"iteration":818,"passed_time":0.3758157238,"remaining_time":0.08305573384},
{"learn":[0.1755427464],"iteration":819,"passed_time":0.3761956837,"remaining_time":0.08257954033},
{"learn":[0.1754302381],"iteration":820,"passed_time":0.3765803525,"remaining_time":0.08210460792},
{"learn":[0.1753819915],"iteration":821,"passed_time":0.3769730365,"remaining_time":0.08163163077},
{"learn":[0.1753444621],"iteration":822,"passed_time":0.3773960678,"remaining_time":0.08116537545},
{"learn":[0.1752472145],"iteration":823,"passed_time":0.3777995121,"remaining_time":0.08069504143},
{"learn":[0.1752153711],"iteration":824,"passed_time":0.3781970854,"remaining_time":0.08022362417},
{"learn":[0.175002644],"iteration":825,"passed_time":0.3786091964,"remaining_time":0.07975544815},
{"learn":[0.1747975443],"iteration":826,"passed_time":0.3790252246,"remaining_time":0.07928822715},
{"learn":[0.1747952575],"iteration":827,"passed_time":0.3793904868,"remaining_time":0.07881058422},
{"learn":[0.1747330387],"iteration":828,"passed_time":0.3797768687,"remaining_time":0.07833756881},
{"learn":[0.1746462817],"iteration":829,"passed_time":0.38019985,"remaining_time":0.07787225844},
{"learn":[0.1745157519],"iteration":830,"passed_time":0.3806131331,"remaining_time":0.0774050776},
{"learn":[0.1745055254],"iteration":831,"passed_time":0.3810137922,"remaining_time":0.07693547726},
{"learn":[0.1743527824],"iteration":832,"passed_time":0.3814195409,"remaining_time":0.07646706282},
{"learn":[0.1742073703],"iteration":833,"passed_time":0.3818427627,"remaining_time":0.07600227651},
{"learn":[0.1741770693],"iteration":834,"passed_time":0.3822354868,"remaining_time":0.07553156326},
{"learn":[0.1740297459],"iteration":835,"passed_time":0.3826413357,"remaining_time":0.07506361131},
{"learn":[0.1740068416],"iteration":836,"passed_time":0.3830502006,"remaining_time":0.07459639509},
{"learn":[0.1739095677],"iteration":837,"passed_time":0.3834521323,"remaining_time":0.07412797784},
{"learn":[0.1738093517],"iteration":838,"passed_time":0.3838796823,"remaining_time":0.0736646351},
{"learn":[0.1737799453],"iteration":839,"passed_time":0.3842735187,"remaining_time":0.07319495594},
{"learn":[0.1737573934],"iteration":840,"passed_time":0.3847295627,"remaining_time":0.07273721816},
{"learn":[0.1737083921],"iteration":841,"passed_time":0.3851227877,"remaining_time":0.07226769651},
{"learn":[0.1736372763],"iteration":842,"passed_time":0.3855416511,"remaining_time":0.07180313075},
{"learn":[0.1734925672],"iteration":843,"passed_time":0.3859428312,"remaining_time":0.07133540482},
{"learn":[0.1734005109],"iteration":844,"passed_time":0.3863344932,"remaining_time":0.07086609047},
{"learn":[0.1733030764],"iteration":845,"passed_time":0.3867571638,"remaining_time":0.07040260429},
{"learn":[0.1733014261],"iteration":846,"passed_time":0.3871321944,"remaining_time":0.0699306089},
{"learn":[0.1732260552],"iteration":847,"passed_time":0.3875396864,"remaining_time":0.06946466077},
{"learn":[0.1730570321],"iteration":848,"passed_time":0.387968038,"remaining_time":0.06900256034},
{"learn":[0.1729391846],"iteration":849,"passed_time":0.3883942455,"remaining_time":0.06854016096},
{"learn":[0.1728835439],"iteration":850,"passed_time":0.3887946743,"remaining_time":0.06807333311},
{"learn":[0.1728403294],"iteration":851,"passed_time":0.3892010442,"remaining_time":0.06760769313},
{"learn":[0.1727505527],"iteration":852,"passed_time":0.3896175035,"remaining_time":0.06714393084},
{"learn":[0.1726786289],"iteration":853,"passed_time":0.3900167902,"remaining_time":0.06667734352},
{"learn":[0.1726738686],"iteration":854,"passed_time":0.3904110571,"remaining_time":0.06621006232},
{"learn":[0.17258003],"iteration":855,"passed_time":0.3908133495,"remaining_time":0.06574430179},
{"learn":[0.1725675209],"iteration":856,"passed_time":0.3912086683,"remaining_time":0.06527752575},
{"learn":[0.1725654448],"iteration":857,"passed_time":0.3915603546,"remaining_time":0.06480369505},
{"learn":[0.1725032176],"iteration":858,"passed_time":0.3919390321,"remaining_time":0.06433457919},
{"learn":[0.1723769118],"iteration":859,"passed_time":0.3923662713,"remaining_time":0.06387357905},
{"learn":[0.1722832504],"iteration":860,"passed_time":0.392758184,"remaining_time":0.06340695422},
{"learn":[0.1721380735],"iteration":861,"passed_time":0.3931775185,"remaining_time":0.06294489276},
{"learn":[0.1720460022],"iteration":862,"passed_time":0.3935746411,"remaining_time":0.06247940421},
{"learn":[0.1720443986],"iteration":863,"passed_time":0.3939524471,"remaining_time":0.06201103334},
{"learn":[0.1719905923],"iteration":864,"passed_time":0.3943416146,"remaining_time":0.06154464506},
{"learn":[0.1719117112],"iteration":865,"passed_time":0.3947427947,"remaining_time":0.06108029387},
{"learn":[0.1718532008],"iteration":866,"passed_time":0.395162159,"remaining_time":0.06061887792},
{"learn":[0.1717536976],"iteration":867,"passed_time":0.3955578589,"remaining_time":0.06015396012},
{"learn":[0.1716754352],"iteration":868,"passed_time":0.3959625457,"remaining_time":0.05969055637},
{"learn":[0.1715498989],"iteration":869,"passed_time":0.3963520134,"remaining_time":0.05922501349},
{"learn":[0.1714163469],"iteration":870,"passed_time":0.3967649557,"remaining_time":0.05876312203},
{"learn":[0.1713336028],"iteration":871,"passed_time":0.3971553652,"remaining_time":0.05829803526},
{"learn":[0.1712441133],"iteration":872,"passed_time":0.3975545415,"remaining_time":0.05783439492},
{"learn":[0.1711671773],"iteration":873,"passed_time":0.3979746975,"remaining_time":0.05737392664},
{"learn":[0.1711598399],"iteration":874,"passed_time":0.3983518218,"remaining_time":0.05690740312},
{"learn":[0.1711286055],"iteration":875,"passed_time":0.3987613176,"remaining_time":0.05644566597},
{"learn":[0.1711052477],"iteration":876,"passed_time":0.3991368892,"remaining_time":0.05597929005},
{"learn":[0.1710982807],"iteration":877,"passed_time":0.3995146048,"remaining_time":0.0555134189},
{"learn":[0.1710955727],"iteration":878,"passed_time":0.3998870906,"remaining_time":0.05504702839},
{"learn":[0.1709481052],"iteration":879,"passed_time":0.4002812373,"remaining_time":0.05458380509},
{"learn":[0.1708725431],"iteration":880,"passed_time":0.4007103401,"remaining_time":0.05412546024},
{"learn":[0.1708350891],"iteration":881,"passed_time":0.4011130128,"remaining_time":0.0536636457},
{"learn":[0.1707601087],"iteration":882,"passed_time":0.4015323272,"remaining_time":0.0532041702},
{"learn":[0.1707583214],"iteration":883,"passed_time":0.4019084599,"remaining_time":0.05273911917},
{"learn":[0.170729026],"iteration":884,"passed_time":0.4022942205,"remaining_time":0.05227552018},
{"learn":[0.1706497203],"iteration":885,"passed_time":0.4027036665,"remaining_time":0.05181514444},
{"learn":[0.1706348289],"iteration":886,"passed_time":0.4030854097,"remaining_time":0.05135135434},
{"learn":[0.1706330961],"iteration":887,"passed_time":0.4034623839,"remaining_time":0.05088714752},
{"learn":[0.170461173],"iteration":888,"passed_time":0.4038648963,"remaining_time":0.05042632564},
{"learn":[0.1704563034],"iteration":889,"passed_time":0.404306513,"remaining_time":0.0499704679},
{"learn":[0.170403054],"iteration":890,"passed_time":0.4046923841,"remaining_time":0.04950782252},
{"learn":[0.1702420294],"iteration":891,"passed_time":0.4050858295,"remaining_time":0.04904626636},
{"learn":[0.1701481428],"iteration":892,"passed_time":0.4055168061,"remaining_time":0.04858935974},
{"learn":[0.1700598977],"iteration":893,"passed_time":0.4059159325,"remaining_time":0.04812873472},
{"learn":[0.1699277326],"iteration":894,"passed_time":0.4063367596,"remaining_time":0.04767079302},
{"learn":[0.169870506],"iteration":895,"passed_time":0.4069997859,"remaining_time":0.04724104658},
{"learn":[0.1697435358],"iteration":896,"passed_time":0.4076065155,"remaining_time":0.0468043156},
{"learn":[0.1696074683],"iteration":897,"passed_time":0.4080305486,"remaining_time":0.0463464543},
{"learn":[0.1695283404],"iteration":898,"passed_time":0.4084410566,"remaining_time":0.04588714874},
{"learn":[0.1693682137],"iteration":899,"passed_time":0.4088437195,"remaining_time":0.04542707994},
{"learn":[0.1693670145],"iteration":900,"passed_time":0.4092299512,"remaining_time":0.04496533316},
{"learn":[0.1693648031],"iteration":901,"passed_time":0.4095860156,"remaining_time":0.0445004762},
{"learn":[0.1692633888],"iteration":902,"passed_time":0.4099876766,"remaining_time":0.04404075818},
{"learn":[0.1691461095],"iteration":903,"passed_time":0.4104046466,"remaining_time":0.04358279433},
{"learn":[0.1690829978],"iteration":904,"passed_time":0.4108263456,"remaining_time":0.04312541749},
{"learn":[0.1688936502],"iteration":905,"passed_time":0.411241953,"remaining_time":0.0426674874},
{"learn":[0.1688023768],"iteration":906,"passed_time":0.4116448163,"remaining_time":0.0422083439},
{"learn":[0.1687090533],"iteration":907,"passed_time":0.4120617364,"remaining_time":0.04175074862},
{"learn":[0.1685670134],"iteration":908,"passed_time":0.412466884,"remaining_time":0.04129206429},
{"learn":[0.1684793606],"iteration":909,"passed_time":0.4128823912,"remaining_time":0.04083452221},
{"learn":[0.1683861734],"iteration":910,"passed_time":0.4132779504,"remaining_time":0.04037512359},
{"learn":[0.1682467933],"iteration":911,"passed_time":0.4136994089,"remaining_time":0.03991836402},
{"learn":[0.1681279728],"iteration":912,"passed_time":0.4141029735,"remaining_time":0.03945997667},
{"learn":[0.1681263401],"iteration":913,"passed_time":0.4144641979,"remaining_time":0.0389977254},
{"learn":[0.1680447133],"iteration":914,"passed_time":0.4148852556,"remaining_time":0.03854125326},
{"learn":[0.1680156425],"iteration":915,"passed_time":0.4152711766,"remaining_time":0.03808163628},
{"learn":[0.1679048026],"iteration":916,"passed_time":0.4156907818,"remaining_time":0.03762522889},
{"learn":[0.1678259502],"iteration":917,"passed_time":0.4161119095,"remaining_time":0.03716903767},
{"learn":[0.167765959],"iteration":918,"passed_time":0.4165308632,"remaining_time":0.03671273114},
{"learn":[0.1676088572],"iteration":919,"passed_time":0.416923557,"remaining_time":0.03625422235},
{"learn":[0.1675922817],"iteration":920,"passed_time":0.417310861,"remaining_time":0.03579539416},
{"learn":[0.1675094609],"iteration":921,"passed_time":0.4177250658,"remaining_time":0.03533899689},
{"learn":[0.1674049046],"iteration":922,"passed_time":0.4181337601,"remaining_time":0.03488223134},
{"learn":[0.1673243232],"iteration":923,"passed_time":0.4185494477,"remaining_time":0.03442614505},
{"learn":[0.1672580302],"iteration":924,"passed_time":0.4189398175,"remaining_time":0.03396809331},
{"learn":[0.1672471378],"iteration":925,"passed_time":0.419356567,"remaining_time":0.03351229585},
{"learn":[0.1671618198],"iteration":926,"passed_time":0.4197658126,"remaining_time":0.03305599172},
{"learn":[0.1670801663],"iteration":927,"passed_time":0.420172032,"remaining_time":0.03259955421},
{"learn":[0.1668858039],"iteration":928,"passed_time":0.420575887,"remaining_time":0.03214304411},
{"learn":[0.1668309548],"iteration":929,"passed_time":0.4209732799,"remaining_time":0.03168616085},
{"learn":[0.1667781144],"iteration":930,"passed_time":0.4213893183,"remaining_time":0.03123078729},
{"learn":[0.166709747],"iteration":931,"passed_time":0.4217875929,"remaining_time":0.03077420206},
{"learn":[0.1665819749],"iteration":932,"passed_time":0.4222173173,"remaining_time":0.03032000028},
{"learn":[0.1664473893],"iteration":933,"passed_time":0.422621483,"remaining_time":0.02986404484},
{"learn":[0.1663640934],"iteration":934,"passed_time":0.4230493038,"remaining_time":0.02940984465},
{"learn":[0.1662527259],"iteration":935,"passed_time":0.4234469772,"remaining_time":0.02895363947},
{"learn":[0.1661510766],"iteration":936,"passed_time":0.4238579358,"remaining_time":0.02849845246},
{"learn":[0.1661348132],"iteration":937,"passed_time":0.424253385,"remaining_time":0.02804233462},
{"learn":[0.1661277728],"iteration":938,"passed_time":0.4246461291,"remaining_time":0.02758617026},
{"learn":[0.1660915306],"iteration":939,"passed_time":0.4250569274,"remaining_time":0.02713129324},
{"learn":[0.1659560843],"iteration":940,"passed_time":0.4254644297,"remaining_time":0.02667630324},
{"learn":[0.1657636045],"iteration":941,"passed_time":0.4258834534,"remaining_time":0.02622212346},
{"learn":[0.165590363],"iteration":942,"passed_time":0.4262946823,"remaining_time":0.02576754707},
{"learn":[0.1655318523],"iteration":943,"passed_time":0.4267055006,"remaining_time":0.02531303817},
{"learn":[0.1654367254],"iteration":944,"passed_time":0.4270985253,"remaining_time":0.02485758613},
{"learn":[0.1653259222],"iteration":945,"passed_time":0.427497421,"remaining_time":0.0244026012},
{"learn":[0.1651916999],"iteration":946,"passed_time":0.4279047826,"remaining_time":0.02394820853},
{"learn":[0.1650747214],"iteration":947,"passed_time":0.4283027865,"remaining_time":0.02349340179},
{"learn":[0.1650076494],"iteration":948,"passed_time":0.4287095571,"remaining_time":0.02303918589},
{"learn":[0.1649060395],"iteration":949,"passed_time":0.4291121599,"remaining_time":0.02258485052},
{"learn":[0.1647520671],"iteration":950,"passed_time":0.4295327969,"remaining_time":0.02213155315},
{"learn":[0.1646483058],"iteration":951,"passed_time":0.4299449676,"remaining_time":0.02167789752},
{"learn":[0.1645573336],"iteration":952,"passed_time":0.4303788594,"remaining_time":0.0212254002},
{"learn":[0.164507703],"iteration":953,"passed_time":0.4308281506,"remaining_time":0.02077368441},
{"learn":[0.1644427642],"iteration":954,"passed_time":0.4312261946,"remaining_time":0.02031955891},
{"learn":[0.1643346511],"iteration":955,"passed_time":0.4316467514,"remaining_time":0.01986658688},
{"learn":[0.1642602132],"iteration":956,"passed_time":0.432061397,"remaining_time":0.019413417},
{"learn":[0.1642512373],"iteration":957,"passed_time":0.4324683578,"remaining_time":0.01895999063},
{"learn":[0.1640963297],"iteration":958,"passed_time":0.4328828733,"remaining_time":0.01850698416},
{"learn":[0.1640293651],"iteration":959,"passed_time":0.4333099928,"remaining_time":0.01805458303},
{"learn":[0.1639720218],"iteration":960,"passed_time":0.4337186172,"remaining_time":0.01760148394},
{"learn":[0.1638376845],"iteration":961,"passed_time":0.4341448349,"remaining_time":0.01714917227},
{"learn":[0.1637077742],"iteration":962,"passed_time":0.4345608831,"remaining_time":0.01669652407},
{"learn":[0.1636469915],"iteration":963,"passed_time":0.4349750981,"remaining_time":0.01624388333},
{"learn":[0.1635466291],"iteration":964,"passed_time":0.435390876,"remaining_time":0.01579137892},
{"learn":[0.1634587527],"iteration":965,"passed_time":0.4357836402,"remaining_time":0.01533814054},
{"learn":[0.163427972],"iteration":966,"passed_time":0.4361989871,"remaining_time":0.01488579791},
{"learn":[0.1634216225],"iteration":967,"passed_time":0.4365802597,"remaining_time":0.01443240528},
{"learn":[0.1633864588],"iteration":968,"passed_time":0.4369863188,"remaining_time":0.01397995447},
{"learn":[0.1632898181],"iteration":969,"passed_time":0.4373982793,"remaining_time":0.01352778183},
{"learn":[0.1632888182],"iteration":970,"passed_time":0.4377760853,"remaining_time":0.01307467196},
{"learn":[0.1631683272],"iteration":971,"passed_time":0.4381842987,"remaining_time":0.01262259297},
{"learn":[0.1631009037],"iteration":972,"passed_time":0.4385745781,"remaining_time":0.01217010648},
{"learn":[0.1629932773],"iteration":973,"passed_time":0.4389870396,"remaining_time":0.01171833987},
{"learn":[0.1629641147],"iteration":974,"passed_time":0.4393868771,"remaining_time":0.01126633018},
{"learn":[0.1629349458],"iteration":975,"passed_time":0.43978963,"remaining_time":0.0108144991},
{"learn":[0.1629338203],"iteration":976,"passed_time":0.4401579077,"remaining_time":0.01036195689},
{"learn":[0.1628207147],"iteration":977,"passed_time":0.4405523951,"remaining_time":0.009910176577},
{"learn":[0.1628196421],"iteration":978,"passed_time":0.4409435763,"remaining_time":0.009458442392},
{"learn":[0.1627687761],"iteration":979,"passed_time":0.4413389053,"remaining_time":0.009006916434},
{"learn":[0.162694781],"iteration":980,"passed_time":0.441775182,"remaining_time":0.008556298123},
{"learn":[0.1625970301],"iteration":981,"passed_time":0.4421786865,"remaining_time":0.008105108307},
{"learn":[0.1625553801],"iteration":982,"passed_time":0.442567814,"remaining_time":0.007653766874},
{"learn":[0.1624515617],"iteration":983,"passed_time":0.4429725207,"remaining_time":0.007202805215},
{"learn":[0.1624088172],"iteration":984,"passed_time":0.4433664871,"remaining_time":0.006751773916},
{"learn":[0.162340318],"iteration":985,"passed_time":0.4437846795,"remaining_time":0.006301202345},
{"learn":[0.1622026779],"iteration":986,"passed_time":0.4442003871,"remaining_time":0.005850663659},
{"learn":[0.1621819764],"iteration":987,"passed_time":0.4446143714,"remaining_time":0.005400174551},
{"learn":[0.1621498053],"iteration":988,"passed_time":0.4449874382,"remaining_time":0.004949304166},
{"learn":[0.1620694309],"iteration":989,"passed_time":0.4454121531,"remaining_time":0.004499112658},
{"learn":[0.1619730784],"iteration":990,"passed_time":0.4458299949,"remaining_time":0.004048910146},
{"learn":[0.161836999],"iteration":991,"passed_time":0.446240022,"remaining_time":0.003598709855},
{"learn":[0.1617341572],"iteration":992,"passed_time":0.4466821597,"remaining_time":0.003148816836},
{"learn":[0.1617269969],"iteration":993,"passed_time":0.4470639929,"remaining_time":0.00269857541},
{"learn":[0.1615974698],"iteration":994,"passed_time":0.4474875353,"remaining_time":0.002248681082},
{"learn":[0.1615411932],"iteration":995,"passed_time":0.4478897877,"remaining_time":0.001798754167},
{"learn":[0.1615267166],"iteration":996,"passed_time":0.4483084306,"remaining_time":0.001348972208},
{"learn":[0.1614553049],"iteration":997,"passed_time":0.4487188081,"remaining_time":0.0008992360884},
{"learn":[0.1614541791],"iteration":998,"passed_time":0.449067108,"remaining_time":0.0004495166246},
{"learn":[0.1613872764],"iteration":999,"passed_time":0.4494818738,"remaining_time":0}
]}